{"data": [{"date": "20230226", "label": "", "histogram": [140, 3570, 14, 1528, 0, 0, 0, 0, 0, 0, 0, 0, 0, 0, 0, 0, 0], "count": 69, "sum": 8182}, {"date": "20230227", "label": "", "histogram": [809, 7119, 10, 1441, 0, 0, 0, 0, 0, 0, 0, 0, 0, 0, 0, 0, 0], "count": 164, "sum": 11462}, {"date": "20230228", "label": "", "histogram": [497, 3700, 15, 200, 0, 0, 0, 0, 0, 0, 0, 0, 0, 0, 0, 0, 0], "count": 123, "sum": 4330}, {"date": "20230301", "label": "", "histogram": [723, 5872, 14, 2271, 0, 0, 0, 0, 0, 0, 0, 0, 0, 0, 0, 0, 0], "count": 151, "sum": 12713}, {"date": "20230302", "label": "", "histogram": [445, 5713, 12, 778, 0, 0, 0, 0, 0, 0, 0, 0, 0, 0, 0, 0, 0], "count": 154, "sum": 8071}, {"date": "20230303", "label": "", "histogram": [1095, 4642, 32, 727, 0, 0, 0, 0, 0, 0, 0, 0, 0, 0, 0, 0, 0], "count": 135, "sum": 6887}, {"date": "20230304", "label": "", "histogram": [161, 3722, 1, 2, 0, 0, 0, 0, 0, 0, 0, 0, 0, 0, 0, 0, 0], "count": 49, "sum": 3730}, {"date": "20230305", "label": "", "histogram": [298, 3856, 60, 36, 0, 0, 0, 0, 0, 0, 0, 0, 0, 0, 0, 0, 0], "count": 69, "sum": 4084}, {"date": "20230306", "label": "", "histogram": [687, 5573, 164, 6, 0, 0, 0, 0, 0, 0, 0, 0, 0, 0, 0, 0, 0], "count": 139, "sum": 5919}, {"date": "20230307", "label": "", "histogram": [357, 5363, 170, 641, 0, 0, 0, 0, 0, 0, 0, 0, 0, 0, 0, 0, 0], "count": 166, "sum": 7626}, {"date": "20230308", "label": "", "histogram": [538, 6608, 150, 765, 0, 0, 0, 0, 0, 0, 0, 0, 0, 0, 0, 0, 0], "count": 164, "sum": 9203}, {"date": "20230309", "label": "", "histogram": [1375, 4945, 152, 721, 0, 0, 0, 0, 0, 0, 0, 0, 0, 0, 0, 0, 0], "count": 200, "sum": 7412}, {"date": "20230310", "label": "", "histogram": [982, 4968, 198, 502, 0, 0, 0, 0, 0, 0, 0, 0, 0, 0, 0, 0, 0], "count": 120, "sum": 6870}, {"date": "20230311", "label": "", "histogram": [163, 3666, 145, 797, 0, 0, 0, 0, 0, 0, 0, 0, 0, 0, 0, 0, 0], "count": 73, "sum": 6347}, {"date": "20230312", "label": "", "histogram": [4136, 3496, 139, 19, 0, 0, 0, 0, 0, 0, 0, 0, 0, 0, 0, 0, 0], "count": 78, "sum": 3831}, {"date": "20230313", "label": "", "histogram": [614, 4944, 172, 39, 0, 0, 0, 0, 0, 0, 0, 0, 0, 0, 0, 0, 0], "count": 100, "sum": 5405}, {"date": "20230314", "label": "", "histogram": [2021, 2779, 162, 1, 0, 0, 0, 0, 0, 0, 0, 0, 0, 0, 0, 0, 0], "count": 76, "sum": 3106}, {"date": "20230315", "label": "", "histogram": [1047, 4207, 195, 27, 0, 0, 0, 0, 0, 0, 0, 0, 0, 0, 0, 0, 0], "count": 85, "sum": 4678}, {"date": "20230316", "label": "", "histogram": [1064, 2428, 135, 0, 0, 0, 0, 0, 0, 0, 0, 0, 0, 0, 0, 0, 0], "count": 59, "sum": 2698}, {"date": "20230317", "label": "", "histogram": [398, 2950, 152, 2, 0, 0, 0, 0, 0, 0, 0, 0, 0, 0, 0, 0, 0], "count": 73, "sum": 3260}, {"date": "20230318", "label": "", "histogram": [169, 1724, 120, 0, 0, 0, 0, 0, 0, 0, 0, 0, 0, 0, 0, 0, 0], "count": 46, "sum": 1964}, {"date": "20230319", "label": "", "histogram": [1852, 2310, 137, 216, 0, 0, 0, 0, 0, 0, 0, 0, 0, 0, 0, 0, 0], "count": 59, "sum": 3232}, {"date": "20230320", "label": "", "histogram": [372, 4542, 129, 140, 0, 0, 0, 0, 0, 0, 0, 0, 0, 0, 0, 0, 0], "count": 70, "sum": 5220}, {"date": "20230321", "label": "", "histogram": [328, 3428, 252, 9, 0, 0, 0, 0, 0, 0, 0, 0, 0, 0, 0, 0, 0], "count": 125, "sum": 3959}, {"date": "20230322", "label": "", "histogram": [430, 5010, 124, 167, 0, 0, 0, 0, 0, 0, 0, 0, 0, 0, 0, 0, 0], "count": 108, "sum": 5759}, {"date": "20230323", "label": "", "histogram": [404, 3798, 32, 40, 0, 0, 0, 0, 0, 0, 0, 0, 0, 0, 0, 0, 0], "count": 116, "sum": 3982}, {"date": "20230324", "label": "", "histogram": [326, 4141, 36, 0, 0, 0, 0, 0, 0, 0, 0, 0, 0, 0, 0, 0, 0], "count": 103, "sum": 4213}, {"date": "20230325", "label": "", "histogram": [210, 3020, 138, 183, 0, 0, 0, 0, 0, 0, 0, 0, 0, 0, 0, 0, 0], "count": 57, "sum": 3845}, {"date": "20230326", "label": "", "histogram": [203, 1623, 125, 165, 0, 0, 0, 0, 0, 0, 0, 0, 0, 0, 0, 0, 0], "count": 47, "sum": 2368}, {"date": "20230327", "label": "", "histogram": [801, 4189, 167, 3, 0, 0, 0, 0, 0, 0, 0, 0, 0, 0, 0, 0, 0], "count": 101, "sum": 4532}, {"date": "20230328", "label": "", "histogram": [345, 3343, 174, 93, 0, 0, 0, 0, 0, 0, 0, 0, 0, 0, 0, 0, 0], "count": 119, "sum": 3970}, {"date": "20230329", "label": "", "histogram": [758, 4227, 210, 2, 0, 0, 0, 0, 0, 0, 0, 0, 0, 0, 0, 0, 0], "count": 108, "sum": 4653}, {"date": "20230330", "label": "", "histogram": [985, 3258, 43, 5, 0, 0, 0, 0, 0, 0, 0, 0, 0, 0, 0, 0, 0], "count": 126, "sum": 3359}, {"date": "20230331", "label": "", "histogram": [926, 4514, 8, 4, 0, 0, 0, 0, 0, 0, 0, 0, 0, 0, 0, 0, 0], "count": 99, "sum": 4542}, {"date": "20230401", "label": "", "histogram": [978, 4427, 4, 157, 0, 0, 0, 0, 0, 0, 0, 0, 0, 0, 0, 0, 0], "count": 50, "sum": 4906}, {"date": "20230402", "label": "", "histogram": [628, 2862, 4, 0, 0, 0, 0, 0, 0, 0, 0, 0, 0, 0, 0, 0, 0], "count": 48, "sum": 2870}, {"date": "20230403", "label": "", "histogram": [1208, 6247, 234, 41, 0, 0, 0, 0, 0, 0, 0, 0, 0, 0, 0, 0, 0], "count": 140, "sum": 6838}, {"date": "20230404", "label": "", "histogram": [1520, 5694, 129, 577, 0, 0, 0, 0, 0, 0, 0, 0, 0, 0, 0, 0, 0], "count": 117, "sum": 7683}, {"date": "20230405", "label": "", "histogram": [340, 3134, 124, 460, 0, 0, 0, 0, 0, 0, 0, 0, 0, 0, 0, 0, 0], "count": 107, "sum": 4762}, {"date": "20230406", "label": "", "histogram": [1350, 5036, 131, 63, 0, 0, 0, 0, 0, 0, 0, 0, 0, 0, 0, 0, 0], "count": 99, "sum": 5487}, {"date": "20230407", "label": "", "histogram": [239, 1734, 177, 0, 0, 0, 0, 0, 0, 0, 0, 0, 0, 0, 0, 0, 0], "count": 54, "sum": 2088}, {"date": "20230408", "label": "", "histogram": [1132, 6702, 97, 242, 0, 0, 0, 0, 0, 0, 0, 0, 0, 0, 0, 0, 0], "count": 64, "sum": 7622}, {"date": "20230409", "label": "", "histogram": [66, 2951, 0, 144, 0, 0, 0, 0, 0, 0, 0, 0, 0, 0, 0, 0, 0], "count": 49, "sum": 3383}, {"date": "20230410", "label": "", "histogram": [2670, 11319, 42, 667, 0, 0, 0, 0, 0, 0, 0, 0, 0, 0, 0, 0, 0], "count": 134, "sum": 13404}, {"date": "20230411", "label": "", "histogram": [585, 4393, 8, 161, 0, 0, 0, 0, 0, 0, 0, 0, 0, 0, 0, 0, 0], "count": 128, "sum": 4892}, {"date": "20230412", "label": "", "histogram": [498, 3453, 11, 364, 0, 0, 0, 0, 0, 0, 0, 0, 0, 0, 0, 0, 0], "count": 120, "sum": 4567}, {"date": "20230413", "label": "", "histogram": [475, 3295, 14, 5, 0, 0, 0, 0, 0, 0, 0, 0, 0, 0, 0, 0, 0], "count": 121, "sum": 3338}, {"date": "20230414", "label": "", "histogram": [687, 4805, 4, 17, 0, 0, 0, 0, 0, 0, 0, 0, 0, 0, 0, 0, 0], "count": 121, "sum": 4864}, {"date": "20230415", "label": "", "histogram": [195, 2837, 0, 0, 0, 0, 0, 0, 0, 0, 0, 0, 0, 0, 0, 0, 0], "count": 43, "sum": 2837}, {"date": "20230416", "label": "", "histogram": [471, 2909, 0, 1, 0, 0, 0, 0, 0, 0, 0, 0, 0, 0, 0, 0, 0], "count": 38, "sum": 2912}, {"date": "20230417", "label": "", "histogram": [537, 4500, 132, 0, 0, 0, 0, 0, 0, 0, 0, 0, 0, 0, 0, 0, 0], "count": 66, "sum": 4764}, {"date": "20230418", "label": "", "histogram": [1366, 6074, 18, 18, 0, 0, 0, 0, 0, 0, 0, 0, 0, 0, 0, 0, 0], "count": 127, "sum": 6164}, {"date": "20230419", "label": "", "histogram": [1682, 8224, 37, 33, 0, 0, 0, 0, 0, 0, 0, 0, 0, 0, 0, 0, 0], "count": 126, "sum": 8397}, {"date": "20230420", "label": "", "histogram": [1232, 3530, 16, 439, 0, 0, 0, 0, 0, 0, 0, 0, 0, 0, 0, 0, 0], "count": 123, "sum": 4879}, {"date": "20230421", "label": "", "histogram": [595, 5219, 19, 466, 0, 0, 0, 0, 0, 0, 0, 0, 0, 0, 0, 0, 0], "count": 124, "sum": 6655}, {"date": "20230422", "label": "", "histogram": [320, 2859, 6, 1, 0, 0, 0, 0, 0, 0, 0, 0, 0, 0, 0, 0, 0], "count": 57, "sum": 2874}, {"date": "20230423", "label": "", "histogram": [247, 2556, 1, 440, 0, 0, 0, 0, 0, 0, 0, 0, 0, 0, 0, 0, 0], "count": 64, "sum": 3878}, {"date": "20230424", "label": "", "histogram": [675, 4049, 1, 4, 0, 0, 0, 0, 0, 0, 0, 0, 0, 0, 0, 0, 0], "count": 126, "sum": 4063}, {"date": "20230425", "label": "", "histogram": [871, 3554, 3, 1277, 0, 0, 0, 0, 0, 0, 0, 0, 0, 0, 0, 0, 0], "count": 86, "sum": 7391}, {"date": "20230426", "label": "", "histogram": [525, 3488, 20, 607, 0, 0, 0, 0, 0, 0, 0, 0, 0, 0, 0, 0, 0], "count": 86, "sum": 5349}, {"date": "20230427", "label": "", "histogram": [383, 3324, 10, 6, 0, 0, 0, 0, 0, 0, 0, 0, 0, 0, 0, 0, 0], "count": 123, "sum": 3362}, {"date": "20230428", "label": "", "histogram": [411, 4000, 5, 1, 0, 0, 0, 0, 0, 0, 0, 0, 0, 0, 0, 0, 0], "count": 112, "sum": 4013}, {"date": "20230429", "label": "", "histogram": [3200, 1842, 1, 0, 0, 0, 0, 0, 0, 0, 0, 0, 0, 0, 0, 0, 0], "count": 60, "sum": 1844}, {"date": "20230430", "label": "", "histogram": [171, 2597, 4, 5, 0, 0, 0, 0, 0, 0, 0, 0, 0, 0, 0, 0, 0], "count": 42, "sum": 2620}, {"date": "20230501", "label": "", "histogram": [185, 5292, 5, 22, 0, 0, 0, 0, 0, 0, 0, 0, 0, 0, 0, 0, 0], "count": 100, "sum": 5368}, {"date": "20230502", "label": "", "histogram": [695, 3601, 6, 0, 0, 0, 0, 0, 0, 0, 0, 0, 0, 0, 0, 0, 0], "count": 77, "sum": 3613}, {"date": "20230503", "label": "", "histogram": [738, 2949, 0, 9, 0, 0, 0, 0, 0, 0, 0, 0, 0, 0, 0, 0, 0], "count": 103, "sum": 2976}, {"date": "20230504", "label": "", "histogram": [591, 2832, 0, 10, 0, 0, 0, 0, 0, 0, 0, 0, 0, 0, 0, 0, 0], "count": 95, "sum": 2862}, {"date": "20230505", "label": "", "histogram": [1506, 4054, 1, 0, 0, 0, 0, 0, 0, 0, 0, 0, 0, 0, 0, 0, 0], "count": 90, "sum": 4056}, {"date": "20230506", "label": "", "histogram": [394, 1965, 1, 0, 0, 0, 0, 0, 0, 0, 0, 0, 0, 0, 0, 0, 0], "count": 44, "sum": 1967}, {"date": "20230507", "label": "", "histogram": [394, 1755, 1, 613, 0, 0, 0, 0, 0, 0, 0, 0, 0, 0, 0, 0, 0], "count": 43, "sum": 3596}, {"date": "20230508", "label": "", "histogram": [1578, 4653, 12, 569, 0, 0, 0, 0, 0, 0, 0, 0, 0, 0, 0, 0, 0], "count": 118, "sum": 6384}, {"date": "20230509", "label": "", "histogram": [770, 3216, 8, 382, 0, 0, 0, 0, 0, 0, 0, 0, 0, 0, 0, 0, 0], "count": 99, "sum": 4378}, {"date": "20230510", "label": "", "histogram": [612, 3483, 60, 381, 0, 0, 0, 0, 0, 0, 0, 0, 0, 0, 0, 0, 0], "count": 95, "sum": 4746}, {"date": "20230511", "label": "", "histogram": [819, 3311, 16, 14, 0, 0, 0, 0, 0, 0, 0, 0, 0, 0, 0, 0, 0], "count": 97, "sum": 3385}, {"date": "20230512", "label": "", "histogram": [817, 2465, 49, 2, 0, 0, 0, 0, 0, 0, 0, 0, 0, 0, 0, 0, 0], "count": 86, "sum": 2569}, {"date": "20230513", "label": "", "histogram": [729, 2376, 2, 0, 0, 0, 0, 0, 0, 0, 0, 0, 0, 0, 0, 0, 0], "count": 49, "sum": 2380}, {"date": "20230514", "label": "", "histogram": [1295, 2928, 0, 4, 0, 0, 0, 0, 0, 0, 0, 0, 0, 0, 0, 0, 0], "count": 61, "sum": 2940}, {"date": "20230515", "label": "", "histogram": [500, 3550, 1, 2, 0, 0, 0, 0, 0, 0, 0, 0, 0, 0, 0, 0, 0], "count": 106, "sum": 3558}, {"date": "20230516", "label": "", "histogram": [447, 3392, 12, 8, 0, 0, 0, 0, 0, 0, 0, 0, 0, 0, 0, 0, 0], "count": 113, "sum": 3440}, {"date": "20230517", "label": "", "histogram": [521, 4928, 97, 5, 0, 0, 0, 0, 0, 0, 0, 0, 0, 0, 0, 0, 0], "count": 121, "sum": 5137}, {"date": "20230518", "label": "", "histogram": [556, 2074, 46, 1, 0, 0, 0, 0, 0, 0, 0, 0, 0, 0, 0, 0, 0], "count": 75, "sum": 2169}, {"date": "20230519", "label": "", "histogram": [729, 4641, 44, 5, 0, 0, 0, 0, 0, 0, 0, 0, 0, 0, 0, 0, 0], "count": 116, "sum": 4744}, {"date": "20230520", "label": "", "histogram": [1460, 4309, 0, 0, 0, 0, 0, 0, 0, 0, 0, 0, 0, 0, 0, 0, 0], "count": 34, "sum": 4309}, {"date": "20230521", "label": "", "histogram": [269, 2423, 2, 1, 0, 0, 0, 0, 0, 0, 0, 0, 0, 0, 0, 0, 0], "count": 56, "sum": 2430}, {"date": "20230522", "label": "", "histogram": [802, 4443, 14, 179, 0, 0, 0, 0, 0, 0, 0, 0, 0, 0, 0, 0, 0], "count": 140, "sum": 5008}, {"date": "20230523", "label": "", "histogram": [484, 3182, 32, 0, 0, 0, 0, 0, 0, 0, 0, 0, 0, 0, 0, 0, 0], "count": 97, "sum": 3246}, {"date": "20230524", "label": "", "histogram": [1872, 3901, 7, 0, 0, 0, 0, 0, 0, 0, 0, 0, 0, 0, 0, 0, 0], "count": 118, "sum": 3915}, {"date": "20230525", "label": "", "histogram": [1674, 4702, 159, 39, 0, 0, 0, 0, 0, 0, 0, 0, 0, 0, 0, 0, 0], "count": 62, "sum": 5137}, {"date": "20230526", "label": "", "histogram": [547, 1692, 223, 0, 0, 0, 0, 0, 0, 0, 0, 0, 0, 0, 0, 0, 0], "count": 52, "sum": 2138}, {"date": "20230527", "label": "", "histogram": [353, 2522, 126, 8, 0, 0, 0, 0, 0, 0, 0, 0, 0, 0, 0, 0, 0], "count": 40, "sum": 2798}, {"date": "20230528", "label": "", "histogram": [465, 2608, 279, 50, 0, 0, 0, 0, 0, 0, 0, 0, 0, 0, 0, 0, 0], "count": 29, "sum": 3316}, {"date": "20230529", "label": "", "histogram": [523, 2416, 17, 100, 0, 0, 0, 0, 0, 0, 0, 0, 0, 0, 0, 0, 0], "count": 53, "sum": 2750}, {"date": "20230530", "label": "", "histogram": [2650, 1042, 5, 4, 0, 0, 0, 0, 0, 0, 0, 0, 0, 0, 0, 0, 0], "count": 41, "sum": 1064}, {"date": "20230531", "label": "", "histogram": [370, 3502, 20, 0, 0, 0, 0, 0, 0, 0, 0, 0, 0, 0, 0, 0, 0], "count": 52, "sum": 3542}, {"date": "20230601", "label": "", "histogram": [185, 2142, 1, 0, 0, 0, 0, 0, 0, 0, 0, 0, 0, 0, 0, 0, 0], "count": 55, "sum": 2144}, {"date": "20230602", "label": "", "histogram": [659, 2147, 5, 0, 0, 0, 0, 0, 0, 0, 0, 0, 0, 0, 0, 0, 0], "count": 48, "sum": 2157}, {"date": "20230603", "label": "", "histogram": [266, 1496, 6, 0, 0, 0, 0, 0, 0, 0, 0, 0, 0, 0, 0, 0, 0], "count": 46, "sum": 1508}, {"date": "20230604", "label": "", "histogram": [240, 3061, 1, 3, 0, 0, 0, 0, 0, 0, 0, 0, 0, 0, 0, 0, 0], "count": 66, "sum": 3072}, {"date": "20230605", "label": "", "histogram": [577, 3105, 12, 0, 0, 0, 0, 0, 0, 0, 0, 0, 0, 0, 0, 0, 0], "count": 73, "sum": 3129}, {"date": "20230606", "label": "", "histogram": [1350, 2497, 67, 0, 0, 0, 0, 0, 0, 0, 0, 0, 0, 0, 0, 0, 0], "count": 76, "sum": 2631}, {"date": "20230607", "label": "", "histogram": [490, 4225, 80, 1, 0, 0, 0, 0, 0, 0, 0, 0, 0, 0, 0, 0, 0], "count": 94, "sum": 4388}, {"date": "20230608", "label": "", "histogram": [654, 3179, 83, 1, 0, 0, 0, 0, 0, 0, 0, 0, 0, 0, 0, 0, 0], "count": 72, "sum": 3348}, {"date": "20230609", "label": "", "histogram": [529, 2653, 72, 0, 0, 0, 0, 0, 0, 0, 0, 0, 0, 0, 0, 0, 0], "count": 55, "sum": 2797}, {"date": "20230610", "label": "", "histogram": [268, 1966, 24, 0, 0, 0, 0, 0, 0, 0, 0, 0, 0, 0, 0, 0, 0], "count": 54, "sum": 2014}, {"date": "20230611", "label": "", "histogram": [130, 1889, 3, 1, 0, 0, 0, 0, 0, 0, 0, 0, 0, 0, 0, 0, 0], "count": 41, "sum": 1898}, {"date": "20230612", "label": "", "histogram": [121, 1438, 5, 0, 0, 0, 0, 0, 0, 0, 0, 0, 0, 0, 0, 0, 0], "count": 47, "sum": 1448}, {"date": "20230613", "label": "", "histogram": [261, 2347, 7, 0, 0, 0, 0, 0, 0, 0, 0, 0, 0, 0, 0, 0, 0], "count": 58, "sum": 2361}, {"date": "20230614", "label": "", "histogram": [140, 2705, 44, 0, 0, 0, 0, 0, 0, 0, 0, 0, 0, 0, 0, 0, 0], "count": 55, "sum": 2793}, {"date": "20230615", "label": "", "histogram": [418, 1477, 105, 0, 0, 0, 0, 0, 0, 0, 0, 0, 0, 0, 0, 0, 0], "count": 48, "sum": 1687}, {"date": "20230616", "label": "", "histogram": [508, 2147, 184, 0, 0, 0, 0, 0, 0, 0, 0, 0, 0, 0, 0, 0, 0], "count": 64, "sum": 2515}, {"date": "20230617", "label": "", "histogram": [131, 3152, 58, 0, 0, 0, 0, 0, 0, 0, 0, 0, 0, 0, 0, 0, 0], "count": 63, "sum": 3268}, {"date": "20230618", "label": "", "histogram": [228, 2494, 7, 0, 0, 0, 0, 0, 0, 0, 0, 0, 0, 0, 0, 0, 0], "count": 53, "sum": 2508}, {"date": "20230619", "label": "", "histogram": [121, 2370, 25, 1, 0, 0, 0, 0, 0, 0, 0, 0, 0, 0, 0, 0, 0], "count": 76, "sum": 2423}, {"date": "20230620", "label": "", "histogram": [241, 2542, 21, 0, 0, 0, 0, 0, 0, 0, 0, 0, 0, 0, 0, 0, 0], "count": 71, "sum": 2584}, {"date": "20230621", "label": "", "histogram": [390, 2849, 24, 7, 0, 0, 0, 0, 0, 0, 0, 0, 0, 0, 0, 0, 0], "count": 48, "sum": 2918}, {"date": "20230622", "label": "", "histogram": [747, 2351, 5, 0, 0, 0, 0, 0, 0, 0, 0, 0, 0, 0, 0, 0, 0], "count": 45, "sum": 2361}, {"date": "20230623", "label": "", "histogram": [146, 1860, 83, 0, 0, 0, 0, 0, 0, 0, 0, 0, 0, 0, 0, 0, 0], "count": 45, "sum": 2026}, {"date": "20230624", "label": "", "histogram": [4557, 2096, 190, 0, 0, 0, 0, 0, 0, 0, 0, 0, 0, 0, 0, 0, 0], "count": 51, "sum": 2476}, {"date": "20230625", "label": "", "histogram": [144, 1599, 192, 0, 0, 0, 0, 0, 0, 0, 0, 0, 0, 0, 0, 0, 0], "count": 39, "sum": 1983}, {"date": "20230626", "label": "", "histogram": [431, 2748, 220, 0, 0, 0, 0, 0, 0, 0, 0, 0, 0, 0, 0, 0, 0], "count": 56, "sum": 3188}, {"date": "20230627", "label": "", "histogram": [1099, 1909, 108, 1, 0, 0, 0, 0, 0, 0, 0, 0, 0, 0, 0, 0, 0], "count": 52, "sum": 2128}, {"date": "20230628", "label": "", "histogram": [393, 2241, 7, 0, 0, 0, 0, 0, 0, 0, 0, 0, 0, 0, 0, 0, 0], "count": 58, "sum": 2255}, {"date": "20230629", "label": "", "histogram": [682, 2390, 28, 0, 0, 0, 0, 0, 0, 0, 0, 0, 0, 0, 0, 0, 0], "count": 66, "sum": 2446}, {"date": "20230630", "label": "", "histogram": [708, 2126, 59, 0, 0, 0, 0, 0, 0, 0, 0, 0, 0, 0, 0, 0, 0], "count": 49, "sum": 2244}, {"date": "20230701", "label": "", "histogram": [577, 2651, 2, 0, 0, 0, 0, 0, 0, 0, 0, 0, 0, 0, 0, 0, 0], "count": 45, "sum": 2655}, {"date": "20230702", "label": "", "histogram": [842, 2129, 17, 0, 0, 0, 0, 0, 0, 0, 0, 0, 0, 0, 0, 0, 0], "count": 23, "sum": 2163}, {"date": "20230703", "label": "", "histogram": [1189, 3248, 15, 0, 0, 0, 0, 0, 0, 0, 0, 0, 0, 0, 0, 0, 0], "count": 59, "sum": 3278}, {"date": "20230704", "label": "", "histogram": [528, 1483, 0, 0, 0, 0, 0, 0, 0, 0, 0, 0, 0, 0, 0, 0, 0], "count": 41, "sum": 1483}, {"date": "20230705", "label": "", "histogram": [535, 2585, 91, 155, 0, 0, 0, 0, 0, 0, 0, 0, 0, 0, 0, 0, 0], "count": 40, "sum": 3232}, {"date": "20230706", "label": "", "histogram": [552, 2545, 29, 0, 0, 0, 0, 0, 0, 0, 0, 0, 0, 0, 0, 0, 0], "count": 47, "sum": 2603}, {"date": "20230707", "label": "", "histogram": [869, 2186, 114, 2, 0, 0, 0, 0, 0, 0, 0, 0, 0, 0, 0, 0, 0], "count": 46, "sum": 2420}, {"date": "20230708", "label": "", "histogram": [299, 2038, 0, 0, 0, 0, 0, 0, 0, 0, 0, 0, 0, 0, 0, 0, 0], "count": 48, "sum": 2038}, {"date": "20230709", "label": "", "histogram": [281, 1772, 0, 0, 0, 0, 0, 0, 0, 0, 0, 0, 0, 0, 0, 0, 0], "count": 36, "sum": 1772}, {"date": "20230710", "label": "", "histogram": [522, 1943, 108, 0, 0, 0, 0, 0, 0, 0, 0, 0, 0, 0, 0, 0, 0], "count": 55, "sum": 2159}, {"date": "20230711", "label": "", "histogram": [240, 2221, 35, 28, 0, 0, 0, 0, 0, 0, 0, 0, 0, 0, 0, 0, 0], "count": 52, "sum": 2375}, {"date": "20230712", "label": "", "histogram": [210, 2798, 0, 0, 0, 0, 0, 0, 0, 0, 0, 0, 0, 0, 0, 0, 0], "count": 41, "sum": 2798}, {"date": "20230713", "label": "", "histogram": [626, 1540, 6, 0, 0, 0, 0, 0, 0, 0, 0, 0, 0, 0, 0, 0, 0], "count": 40, "sum": 1552}, {"date": "20230714", "label": "", "histogram": [190, 1329, 217, 0, 0, 0, 0, 0, 0, 0, 0, 0, 0, 0, 0, 0, 0], "count": 32, "sum": 1763}, {"date": "20230715", "label": "", "histogram": [3742, 2671, 227, 0, 0, 0, 0, 0, 0, 0, 0, 0, 0, 0, 0, 0, 0], "count": 43, "sum": 3125}, {"date": "20230716", "label": "", "histogram": [747, 1784, 5, 1, 0, 0, 0, 0, 0, 0, 0, 0, 0, 0, 0, 0, 0], "count": 33, "sum": 1797}, {"date": "20230717", "label": "", "histogram": [651, 1350, 140, 0, 0, 0, 0, 0, 0, 0, 0, 0, 0, 0, 0, 0, 0], "count": 47, "sum": 1630}, {"date": "20230718", "label": "", "histogram": [518, 2115, 51, 0, 0, 0, 0, 0, 0, 0, 0, 0, 0, 0, 0, 0, 0], "count": 42, "sum": 2217}, {"date": "20230719", "label": "", "histogram": [421, 1629, 48, 1, 0, 0, 0, 0, 0, 0, 0, 0, 0, 0, 0, 0, 0], "count": 43, "sum": 1728}, {"date": "20230720", "label": "", "histogram": [325, 1779, 99, 0, 0, 0, 0, 0, 0, 0, 0, 0, 0, 0, 0, 0, 0], "count": 35, "sum": 1977}, {"date": "20230721", "label": "", "histogram": [455, 1538, 25, 0, 0, 0, 0, 0, 0, 0, 0, 0, 0, 0, 0, 0, 0], "count": 41, "sum": 1588}, {"date": "20230722", "label": "", "histogram": [135, 1711, 4, 0, 0, 0, 0, 0, 0, 0, 0, 0, 0, 0, 0, 0, 0], "count": 38, "sum": 1719}, {"date": "20230723", "label": "", "histogram": [185, 1003, 6, 7, 0, 0, 0, 0, 0, 0, 0, 0, 0, 0, 0, 0, 0], "count": 23, "sum": 1036}, {"date": "20230724", "label": "", "histogram": [2139, 2935, 137, 61, 0, 0, 0, 0, 0, 0, 0, 0, 0, 0, 0, 0, 0], "count": 74, "sum": 3392}, {"date": "20230725", "label": "", "histogram": [162, 2359, 307, 0, 0, 0, 0, 0, 0, 0, 0, 0, 0, 0, 0, 0, 0], "count": 41, "sum": 2973}, {"date": "20230726", "label": "", "histogram": [304, 2210, 27, 1, 0, 0, 0, 0, 0, 0, 0, 0, 0, 0, 0, 0, 0], "count": 50, "sum": 2267}, {"date": "20230727", "label": "", "histogram": [188, 2372, 2, 0, 0, 0, 0, 0, 0, 0, 0, 0, 0, 0, 0, 0, 0], "count": 47, "sum": 2376}, {"date": "20230728", "label": "", "histogram": [258, 2595, 3, 284, 0, 0, 0, 0, 0, 0, 0, 0, 0, 0, 0, 0, 0], "count": 54, "sum": 3453}, {"date": "20230729", "label": "", "histogram": [193, 2379, 1, 0, 0, 0, 0, 0, 0, 0, 0, 0, 0, 0, 0, 0, 0], "count": 37, "sum": 2381}, {"date": "20230730", "label": "", "histogram": [150, 1566, 0, 0, 0, 0, 0, 0, 0, 0, 0, 0, 0, 0, 0, 0, 0], "count": 35, "sum": 1566}, {"date": "20230731", "label": "", "histogram": [129, 2084, 1, 1, 0, 0, 0, 0, 0, 0, 0, 0, 0, 0, 0, 0, 0], "count": 61, "sum": 2089}, {"date": "20230801", "label": "", "histogram": [585, 1669, 0, 21, 0, 0, 0, 0, 0, 0, 0, 0, 0, 0, 0, 0, 0], "count": 40, "sum": 1732}, {"date": "20230802", "label": "", "histogram": [94, 2090, 215, 193, 0, 0, 0, 0, 0, 0, 0, 0, 0, 0, 0, 0, 0], "count": 43, "sum": 3099}, {"date": "20230803", "label": "", "histogram": [111, 1257, 41, 339, 0, 0, 0, 0, 0, 0, 0, 0, 0, 0, 0, 0, 0], "count": 37, "sum": 2356}, {"date": "20230804", "label": "", "histogram": [65, 2580, 8, 8, 0, 0, 0, 0, 0, 0, 0, 0, 0, 0, 0, 0, 0], "count": 38, "sum": 2620}, {"date": "20230805", "label": "", "histogram": [52, 1601, 4, 0, 0, 0, 0, 0, 0, 0, 0, 0, 0, 0, 0, 0, 0], "count": 19, "sum": 1609}, {"date": "20230806", "label": "", "histogram": [32, 1891, 0, 0, 0, 0, 0, 0, 0, 0, 0, 0, 0, 0, 0, 0, 0], "count": 48, "sum": 1891}, {"date": "20230807", "label": "", "histogram": [122, 2487, 1, 0, 0, 0, 0, 0, 0, 0, 0, 0, 0, 0, 0, 0, 0], "count": 36, "sum": 2489}, {"date": "20230808", "label": "", "histogram": [109, 1821, 2, 39, 0, 0, 0, 0, 0, 0, 0, 0, 0, 0, 0, 0, 0], "count": 36, "sum": 1942}, {"date": "20230809", "label": "", "histogram": [99, 2212, 3, 10, 0, 0, 0, 0, 0, 0, 0, 0, 0, 0, 0, 0, 0], "count": 44, "sum": 2248}, {"date": "20230810", "label": "", "histogram": [107, 1191, 0, 0, 0, 0, 0, 0, 0, 0, 0, 0, 0, 0, 0, 0, 0], "count": 33, "sum": 1191}, {"date": "20230811", "label": "", "histogram": [248, 2357, 7, 0, 0, 0, 0, 0, 0, 0, 0, 0, 0, 0, 0, 0, 0], "count": 45, "sum": 2371}, {"date": "20230812", "label": "", "histogram": [423, 860, 2, 0, 0, 0, 0, 0, 0, 0, 0, 0, 0, 0, 0, 0, 0], "count": 24, "sum": 864}, {"date": "20230813", "label": "", "histogram": [325, 1855, 0, 0, 0, 0, 0, 0, 0, 0, 0, 0, 0, 0, 0, 0, 0], "count": 23, "sum": 1855}, {"date": "20230814", "label": "", "histogram": [315, 2093, 5, 8, 0, 0, 0, 0, 0, 0, 0, 0, 0, 0, 0, 0, 0], "count": 36, "sum": 2127}, {"date": "20230815", "label": "", "histogram": [303, 2159, 6, 0, 0, 0, 0, 0, 0, 0, 0, 0, 0, 0, 0, 0, 0], "count": 34, "sum": 2171}, {"date": "20230816", "label": "", "histogram": [150, 2559, 0, 1, 0, 0, 0, 0, 0, 0, 0, 0, 0, 0, 0, 0, 0], "count": 50, "sum": 2562}, {"date": "20230817", "label": "", "histogram": [562, 1935, 2, 2, 0, 0, 0, 0, 0, 0, 0, 0, 0, 0, 0, 0, 0], "count": 38, "sum": 1945}, {"date": "20230818", "label": "", "histogram": [574, 1697, 1, 2, 0, 0, 0, 0, 0, 0, 0, 0, 0, 0, 0, 0, 0], "count": 43, "sum": 1705}, {"date": "20230819", "label": "", "histogram": [1952, 2238, 1, 0, 0, 0, 0, 0, 0, 0, 0, 0, 0, 0, 0, 0, 0], "count": 35, "sum": 2240}, {"date": "20230820", "label": "", "histogram": [3659, 2010, 0, 0, 0, 0, 0, 0, 0, 0, 0, 0, 0, 0, 0, 0, 0], "count": 35, "sum": 2010}, {"date": "20230821", "label": "", "histogram": [23, 809, 0, 0, 0, 0, 0, 0, 0, 0, 0, 0, 0, 0, 0, 0, 0], "count": 22, "sum": 809}, {"date": "20230822", "label": "", "histogram": [599, 3216, 2, 0, 0, 0, 0, 0, 0, 0, 0, 0, 0, 0, 0, 0, 0], "count": 54, "sum": 3220}, {"date": "20230823", "label": "", "histogram": [159, 3983, 0, 0, 0, 0, 0, 0, 0, 0, 0, 0, 0, 0, 0, 0, 0], "count": 57, "sum": 3983}, {"date": "20230824", "label": "", "histogram": [56, 1568, 1, 0, 0, 0, 0, 0, 0, 0, 0, 0, 0, 0, 0, 0, 0], "count": 57, "sum": 1570}, {"date": "20230825", "label": "", "histogram": [68, 1565, 3, 0, 0, 0, 0, 0, 0, 0, 0, 0, 0, 0, 0, 0, 0], "count": 64, "sum": 1571}, {"date": "20230826", "label": "", "histogram": [124, 1090, 2, 0, 0, 0, 0, 0, 0, 0, 0, 0, 0, 0, 0, 0, 0], "count": 31, "sum": 1094}, {"date": "20230827", "label": "", "histogram": [47, 1629, 0, 0, 0, 0, 0, 0, 0, 0, 0, 0, 0, 0, 0, 0, 0], "count": 26, "sum": 1629}, {"date": "20230828", "label": "", "histogram": [87, 1906, 1, 0, 0, 0, 0, 0, 0, 0, 0, 0, 0, 0, 0, 0, 0], "count": 54, "sum": 1908}, {"date": "20230829", "label": "", "histogram": [303, 1472, 1, 0, 0, 0, 0, 0, 0, 0, 0, 0, 0, 0, 0, 0, 0], "count": 37, "sum": 1474}, {"date": "20230830", "label": "", "histogram": [415, 2725, 0, 4, 0, 0, 0, 0, 0, 0, 0, 0, 0, 0, 0, 0, 0], "count": 56, "sum": 2737}, {"date": "20230831", "label": "", "histogram": [455, 1946, 3, 0, 0, 0, 0, 0, 0, 0, 0, 0, 0, 0, 0, 0, 0], "count": 51, "sum": 1952}, {"date": "20230901", "label": "", "histogram": [481, 2490, 0, 0, 0, 0, 0, 0, 0, 0, 0, 0, 0, 0, 0, 0, 0], "count": 47, "sum": 2490}, {"date": "20230902", "label": "", "histogram": [42, 1773, 0, 0, 0, 0, 0, 0, 0, 0, 0, 0, 0, 0, 0, 0, 0], "count": 23, "sum": 1773}, {"date": "20230903", "label": "", "histogram": [46, 1569, 0, 0, 0, 0, 0, 0, 0, 0, 0, 0, 0, 0, 0, 0, 0], "count": 24, "sum": 1569}, {"date": "20230904", "label": "", "histogram": [182, 950, 1, 0, 0, 0, 0, 0, 0, 0, 0, 0, 0, 0, 0, 0, 0], "count": 30, "sum": 952}, {"date": "20230905", "label": "", "histogram": [231, 2934, 7, 2, 0, 0, 0, 0, 0, 0, 0, 0, 0, 0, 0, 0, 0], "count": 48, "sum": 2954}, {"date": "20230906", "label": "", "histogram": [74, 2865, 0, 0, 0, 0, 0, 0, 0, 0, 0, 0, 0, 0, 0, 0, 0], "count": 44, "sum": 2865}, {"date": "20230907", "label": "", "histogram": [95, 1938, 53, 0, 0, 0, 0, 0, 0, 0, 0, 0, 0, 0, 0, 0, 0], "count": 54, "sum": 2044}, {"date": "20230908", "label": "", "histogram": [289, 1316, 0, 0, 0, 0, 0, 0, 0, 0, 0, 0, 0, 0, 0, 0, 0], "count": 37, "sum": 1316}, {"date": "20230909", "label": "", "histogram": [107, 2594, 195, 31, 0, 0, 0, 0, 0, 0, 0, 0, 0, 0, 0, 0, 0], "count": 22, "sum": 3077}, {"date": "20230910", "label": "", "histogram": [30, 1476, 161, 2, 0, 0, 0, 0, 0, 0, 0, 0, 0, 0, 0, 0, 0], "count": 23, "sum": 1804}, {"date": "20230911", "label": "", "histogram": [411, 1362, 138, 0, 0, 0, 0, 0, 0, 0, 0, 0, 0, 0, 0, 0, 0], "count": 39, "sum": 1638}, {"date": "20230912", "label": "", "histogram": [747, 4091, 2, 3, 0, 0, 0, 0, 0, 0, 0, 0, 0, 0, 0, 0, 0], "count": 68, "sum": 4104}, {"date": "20230913", "label": "", "histogram": [148, 2563, 0, 0, 0, 0, 0, 0, 0, 0, 0, 0, 0, 0, 0, 0, 0], "count": 52, "sum": 2563}, {"date": "20230914", "label": "", "histogram": [72, 1529, 0, 1, 0, 0, 0, 0, 0, 0, 0, 0, 0, 0, 0, 0, 0], "count": 43, "sum": 1532}, {"date": "20230915", "label": "", "histogram": [258, 3116, 4, 0, 0, 0, 0, 0, 0, 0, 0, 0, 0, 0, 0, 0, 0], "count": 62, "sum": 3124}, {"date": "20230916", "label": "", "histogram": [65, 2509, 0, 0, 0, 0, 0, 0, 0, 0, 0, 0, 0, 0, 0, 0, 0], "count": 35, "sum": 2509}, {"date": "20230917", "label": "", "histogram": [936, 2669, 0, 0, 0, 0, 0, 0, 0, 0, 0, 0, 0, 0, 0, 0, 0], "count": 18, "sum": 2669}, {"date": "20230918", "label": "", "histogram": [1813, 2337, 1, 1, 0, 0, 0, 0, 0, 0, 0, 0, 0, 0, 0, 0, 0], "count": 50, "sum": 2342}, {"date": "20230919", "label": "", "histogram": [456, 1725, 0, 0, 0, 0, 0, 0, 0, 0, 0, 0, 0, 0, 0, 0, 0], "count": 47, "sum": 1725}, {"date": "20230920", "label": "", "histogram": [5097, 2935, 1, 0, 0, 0, 0, 0, 0, 0, 0, 0, 0, 0, 0, 0, 0], "count": 69, "sum": 2937}, {"date": "20230921", "label": "", "histogram": [704, 2388, 117, 5, 0, 0, 0, 0, 0, 0, 0, 0, 0, 0, 0, 0, 0], "count": 54, "sum": 2637}, {"date": "20230922", "label": "", "histogram": [73, 1605, 69, 14, 0, 0, 0, 0, 0, 0, 0, 0, 0, 0, 0, 0, 0], "count": 51, "sum": 1785}, {"date": "20230923", "label": "", "histogram": [4431, 2671, 3, 0, 0, 0, 0, 0, 0, 0, 0, 0, 0, 0, 0, 0, 0], "count": 46, "sum": 2677}, {"date": "20230924", "label": "", "histogram": [77, 1911, 0, 0, 0, 0, 0, 0, 0, 0, 0, 0, 0, 0, 0, 0, 0], "count": 22, "sum": 1911}, {"date": "20230925", "label": "", "histogram": [550, 1806, 0, 2, 0, 0, 0, 0, 0, 0, 0, 0, 0, 0, 0, 0, 0], "count": 53, "sum": 1812}, {"date": "20230926", "label": "", "histogram": [897, 2316, 0, 1, 0, 0, 0, 0, 0, 0, 0, 0, 0, 0, 0, 0, 0], "count": 44, "sum": 2319}, {"date": "20230927", "label": "", "histogram": [188, 2414, 0, 1, 0, 0, 0, 0, 0, 0, 0, 0, 0, 0, 0, 0, 0], "count": 62, "sum": 2417}, {"date": "20230928", "label": "", "histogram": [566, 2979, 5, 0, 0, 0, 0, 0, 0, 0, 0, 0, 0, 0, 0, 0, 0], "count": 52, "sum": 2989}, {"date": "20230929", "label": "", "histogram": [539, 2439, 2, 0, 0, 0, 0, 0, 0, 0, 0, 0, 0, 0, 0, 0, 0], "count": 58, "sum": 2443}, {"date": "20230930", "label": "", "histogram": [848, 1636, 0, 0, 0, 0, 0, 0, 0, 0, 0, 0, 0, 0, 0, 0, 0], "count": 29, "sum": 1636}, {"date": "20231001", "label": "", "histogram": [279, 1273, 0, 0, 0, 0, 0, 0, 0, 0, 0, 0, 0, 0, 0, 0, 0], "count": 26, "sum": 1273}, {"date": "20231002", "label": "", "histogram": [1352, 5597, 7, 1, 0, 0, 0, 0, 0, 0, 0, 0, 0, 0, 0, 0, 0], "count": 78, "sum": 5614}, {"date": "20231003", "label": "", "histogram": [134, 1579, 4, 0, 0, 0, 0, 0, 0, 0, 0, 0, 0, 0, 0, 0, 0], "count": 47, "sum": 1587}, {"date": "20231004", "label": "", "histogram": [205, 3111, 3, 1, 0, 0, 0, 0, 0, 0, 0, 0, 0, 0, 0, 0, 0], "count": 61, "sum": 3120}, {"date": "20231005", "label": "", "histogram": [2834, 2426, 44, 0, 0, 0, 0, 0, 0, 0, 0, 0, 0, 0, 0, 0, 0], "count": 60, "sum": 2514}, {"date": "20231006", "label": "", "histogram": [88, 1867, 0, 0, 0, 0, 0, 0, 0, 0, 0, 0, 0, 0, 0, 0, 0], "count": 52, "sum": 1867}, {"date": "20220719", "label": "", "histogram": [1632, 12274, 154, 262, 0, 0, 0, 0, 0, 0, 0, 0, 0, 0, 0, 0, 0], "count": 290, "sum": 13368}, {"date": "20220720", "label": "", "histogram": [3515, 15384, 36, 329, 0, 0, 0, 0, 0, 0, 0, 0, 0, 0, 0, 0, 0], "count": 306, "sum": 16443}, {"date": "20220721", "label": "", "histogram": [1656, 12479, 265, 4, 0, 0, 0, 0, 0, 0, 0, 0, 0, 0, 0, 0, 0], "count": 267, "sum": 13021}, {"date": "20220722", "label": "", "histogram": [1223, 11184, 328, 3, 0, 0, 0, 0, 0, 0, 0, 0, 0, 0, 0, 0, 0], "count": 234, "sum": 11849}, {"date": "20220723", "label": "", "histogram": [1335, 9619, 5, 2, 0, 0, 0, 0, 0, 0, 0, 0, 0, 0, 0, 0, 0], "count": 212, "sum": 9635}, {"date": "20220724", "label": "", "histogram": [1035, 9037, 22, 3, 0, 0, 0, 0, 0, 0, 0, 0, 0, 0, 0, 0, 0], "count": 176, "sum": 9090}, {"date": "20220725", "label": "", "histogram": [1612, 10147, 31, 4, 0, 0, 0, 0, 0, 0, 0, 0, 0, 0, 0, 0, 0], "count": 241, "sum": 10221}, {"date": "20220726", "label": "", "histogram": [1726, 10473, 156, 3, 0, 0, 0, 0, 0, 0, 0, 0, 0, 0, 0, 0, 0], "count": 236, "sum": 10794}, {"date": "20220727", "label": "", "histogram": [2418, 10383, 12, 391, 0, 0, 0, 0, 0, 0, 0, 0, 0, 0, 0, 0, 0], "count": 247, "sum": 11580}, {"date": "20220728", "label": "", "histogram": [1780, 11561, 129, 10, 0, 0, 0, 0, 0, 0, 0, 0, 0, 0, 0, 0, 0], "count": 252, "sum": 11849}, {"date": "20220729", "label": "", "histogram": [1424, 13163, 116, 451, 0, 0, 0, 0, 0, 0, 0, 0, 0, 0, 0, 0, 0], "count": 239, "sum": 14748}, {"date": "20220730", "label": "", "histogram": [988, 11216, 112, 0, 0, 0, 0, 0, 0, 0, 0, 0, 0, 0, 0, 0, 0], "count": 194, "sum": 11440}, {"date": "20220731", "label": "", "histogram": [1591, 9403, 103, 35, 0, 0, 0, 0, 0, 0, 0, 0, 0, 0, 0, 0, 0], "count": 169, "sum": 9714}, {"date": "20220801", "label": "", "histogram": [1403, 12485, 64, 1, 0, 0, 0, 0, 0, 0, 0, 0, 0, 0, 0, 0, 0], "count": 224, "sum": 12616}, {"date": "20220802", "label": "", "histogram": [1511, 11112, 187, 4, 0, 0, 0, 0, 0, 0, 0, 0, 0, 0, 0, 0, 0], "count": 233, "sum": 11498}, {"date": "20220803", "label": "", "histogram": [2452, 13981, 28, 157, 0, 0, 0, 0, 0, 0, 0, 0, 0, 0, 0, 0, 0], "count": 314, "sum": 14508}, {"date": "20220804", "label": "", "histogram": [1331, 13662, 3, 6, 0, 0, 0, 0, 0, 0, 0, 0, 0, 0, 0, 0, 0], "count": 263, "sum": 13686}, {"date": "20220805", "label": "", "histogram": [1830, 12589, 52, 0, 0, 0, 0, 0, 0, 0, 0, 0, 0, 0, 0, 0, 0], "count": 246, "sum": 12693}, {"date": "20220806", "label": "", "histogram": [890, 10028, 7, 1, 0, 0, 0, 0, 0, 0, 0, 0, 0, 0, 0, 0, 0], "count": 177, "sum": 10045}, {"date": "20220807", "label": "", "histogram": [1351, 9023, 14, 0, 0, 0, 0, 0, 0, 0, 0, 0, 0, 0, 0, 0, 0], "count": 189, "sum": 9051}, {"date": "20220808", "label": "", "histogram": [1222, 12189, 71, 260, 0, 0, 0, 0, 0, 0, 0, 0, 0, 0, 0, 0, 0], "count": 287, "sum": 13111}, {"date": "20220809", "label": "", "histogram": [1389, 13389, 39, 1, 0, 0, 0, 0, 0, 0, 0, 0, 0, 0, 0, 0, 0], "count": 256, "sum": 13470}, {"date": "20220810", "label": "", "histogram": [2322, 15756, 95, 6, 0, 0, 0, 0, 0, 0, 0, 0, 0, 0, 0, 0, 0], "count": 309, "sum": 15964}, {"date": "20220811", "label": "", "histogram": [1590, 15600, 25, 3, 0, 0, 0, 0, 0, 0, 0, 0, 0, 0, 0, 0, 0], "count": 254, "sum": 15659}, {"date": "20220812", "label": "", "histogram": [1294, 15078, 59, 0, 0, 0, 0, 0, 0, 0, 0, 0, 0, 0, 0, 0, 0], "count": 262, "sum": 15196}, {"date": "20220813", "label": "", "histogram": [1427, 13354, 120, 0, 0, 0, 0, 0, 0, 0, 0, 0, 0, 0, 0, 0, 0], "count": 179, "sum": 13594}, {"date": "20220814", "label": "", "histogram": [1274, 10234, 26, 346, 0, 0, 0, 0, 0, 0, 0, 0, 0, 0, 0, 0, 0], "count": 184, "sum": 11324}, {"date": "20220815", "label": "", "histogram": [1403, 9641, 42, 46, 0, 0, 0, 0, 0, 0, 0, 0, 0, 0, 0, 0, 0], "count": 201, "sum": 9863}, {"date": "20220816", "label": "", "histogram": [1237, 10740, 48, 102, 0, 0, 0, 0, 0, 0, 0, 0, 0, 0, 0, 0, 0], "count": 218, "sum": 11142}, {"date": "20220817", "label": "", "histogram": [3554, 14809, 118, 10, 0, 0, 0, 0, 0, 0, 0, 0, 0, 0, 0, 0, 0], "count": 241, "sum": 15075}, {"date": "20220818", "label": "", "histogram": [2212, 10024, 90, 37, 0, 0, 0, 0, 0, 0, 0, 0, 0, 0, 0, 0, 0], "count": 207, "sum": 10315}, {"date": "20220819", "label": "", "histogram": [6027, 12449, 115, 48, 0, 0, 0, 0, 0, 0, 0, 0, 0, 0, 0, 0, 0], "count": 221, "sum": 12823}, {"date": "20220820", "label": "", "histogram": [3834, 9402, 46, 14, 0, 0, 0, 0, 0, 0, 0, 0, 0, 0, 0, 0, 0], "count": 159, "sum": 9536}, {"date": "20220821", "label": "", "histogram": [6542, 10121, 72, 80, 0, 0, 0, 0, 0, 0, 0, 0, 0, 0, 0, 0, 0], "count": 175, "sum": 10505}, {"date": "20220822", "label": "", "histogram": [3703, 12321, 65, 37, 0, 0, 0, 0, 0, 0, 0, 0, 0, 0, 0, 0, 0], "count": 279, "sum": 12562}, {"date": "20220823", "label": "", "histogram": [5166, 12541, 73, 38, 0, 0, 0, 0, 0, 0, 0, 0, 0, 0, 0, 0, 0], "count": 253, "sum": 12801}, {"date": "20220824", "label": "", "histogram": [6318, 14826, 94, 51, 0, 0, 0, 0, 0, 0, 0, 0, 0, 0, 0, 0, 0], "count": 239, "sum": 15167}, {"date": "20220825", "label": "", "histogram": [5345, 15479, 91, 1, 0, 0, 0, 0, 0, 0, 0, 0, 0, 0, 0, 0, 0], "count": 227, "sum": 15664}, {"date": "20220826", "label": "", "histogram": [2044, 10111, 213, 1, 0, 0, 0, 0, 0, 0, 0, 0, 0, 0, 0, 0, 0], "count": 206, "sum": 10540}, {"date": "20220827", "label": "", "histogram": [3047, 15284, 26, 1, 0, 0, 0, 0, 0, 0, 0, 0, 0, 0, 0, 0, 0], "count": 172, "sum": 15339}, {"date": "20220828", "label": "", "histogram": [4528, 12596, 26, 0, 0, 0, 0, 0, 0, 0, 0, 0, 0, 0, 0, 0, 0], "count": 160, "sum": 12648}, {"date": "20220829", "label": "", "histogram": [3088, 15034, 77, 87, 0, 0, 0, 0, 0, 0, 0, 0, 0, 0, 0, 0, 0], "count": 263, "sum": 15449}, {"date": "20220830", "label": "", "histogram": [3031, 12505, 174, 3, 0, 0, 0, 0, 0, 0, 0, 0, 0, 0, 0, 0, 0], "count": 222, "sum": 12862}, {"date": "20220831", "label": "", "histogram": [1829, 12489, 123, 0, 0, 0, 0, 0, 0, 0, 0, 0, 0, 0, 0, 0, 0], "count": 205, "sum": 12735}, {"date": "20220901", "label": "", "histogram": [1919, 12035, 160, 1, 0, 0, 0, 0, 0, 0, 0, 0, 0, 0, 0, 0, 0], "count": 193, "sum": 12358}, {"date": "20220902", "label": "", "histogram": [1383, 11513, 64, 1, 0, 0, 0, 0, 0, 0, 0, 0, 0, 0, 0, 0, 0], "count": 250, "sum": 11644}, {"date": "20220903", "label": "", "histogram": [853, 10507, 90, 0, 0, 0, 0, 0, 0, 0, 0, 0, 0, 0, 0, 0, 0], "count": 172, "sum": 10687}, {"date": "20220904", "label": "", "histogram": [1470, 9561, 95, 273, 0, 0, 0, 0, 0, 0, 0, 0, 0, 0, 0, 0, 0], "count": 158, "sum": 10570}, {"date": "20220905", "label": "", "histogram": [1138, 9568, 97, 55, 0, 0, 0, 0, 0, 0, 0, 0, 0, 0, 0, 0, 0], "count": 219, "sum": 9927}, {"date": "20220906", "label": "", "histogram": [1738, 13424, 33, 788, 0, 0, 0, 0, 0, 0, 0, 0, 0, 0, 0, 0, 0], "count": 224, "sum": 15854}, {"date": "20220907", "label": "", "histogram": [1294, 11751, 112, 243, 0, 0, 0, 0, 0, 0, 0, 0, 0, 0, 0, 0, 0], "count": 277, "sum": 12704}, {"date": "20220908", "label": "", "histogram": [1350, 10343, 36, 1027, 0, 0, 0, 0, 0, 0, 0, 0, 0, 0, 0, 0, 0], "count": 200, "sum": 13496}, {"date": "20220909", "label": "", "histogram": [1980, 9787, 67, 284, 0, 0, 0, 0, 0, 0, 0, 0, 0, 0, 0, 0, 0], "count": 214, "sum": 10773}, {"date": "20220910", "label": "", "histogram": [1002, 13421, 5, 832, 0, 0, 0, 0, 0, 0, 0, 0, 0, 0, 0, 0, 0], "count": 136, "sum": 15927}, {"date": "20220911", "label": "", "histogram": [3608, 12951, 57, 1131, 0, 0, 0, 0, 0, 0, 0, 0, 0, 0, 0, 0, 0], "count": 246, "sum": 16458}, {"date": "20220912", "label": "", "histogram": [1680, 12035, 170, 1253, 0, 0, 0, 0, 0, 0, 0, 0, 0, 0, 0, 0, 0], "count": 238, "sum": 16134}, {"date": "20220913", "label": "", "histogram": [2695, 12665, 107, 518, 0, 0, 0, 0, 0, 0, 0, 0, 0, 0, 0, 0, 0], "count": 277, "sum": 14433}, {"date": "20220914", "label": "", "histogram": [2327, 12638, 17, 888, 0, 0, 0, 0, 0, 0, 0, 0, 0, 0, 0, 0, 0], "count": 246, "sum": 15336}, {"date": "20220915", "label": "", "histogram": [1357, 11574, 24, 689, 0, 0, 0, 0, 0, 0, 0, 0, 0, 0, 0, 0, 0], "count": 219, "sum": 13689}, {"date": "20220916", "label": "", "histogram": [1296, 11205, 86, 666, 0, 0, 0, 0, 0, 0, 0, 0, 0, 0, 0, 0, 0], "count": 236, "sum": 13375}, {"date": "20220917", "label": "", "histogram": [1606, 9950, 88, 9, 0, 0, 0, 0, 0, 0, 0, 0, 0, 0, 0, 0, 0], "count": 179, "sum": 10153}, {"date": "20220918", "label": "", "histogram": [1306, 7501, 71, 336, 0, 0, 0, 0, 0, 0, 0, 0, 0, 0, 0, 0, 0], "count": 154, "sum": 8651}, {"date": "20220919", "label": "", "histogram": [2610, 13037, 192, 405, 0, 0, 0, 0, 0, 0, 0, 0, 0, 0, 0, 0, 0], "count": 209, "sum": 14636}, {"date": "20220920", "label": "", "histogram": [1606, 12033, 24, 378, 0, 0, 0, 0, 0, 0, 0, 0, 0, 0, 0, 0, 0], "count": 259, "sum": 13215}, {"date": "20220921", "label": "", "histogram": [1936, 11404, 43, 563, 0, 0, 0, 0, 0, 0, 0, 0, 0, 0, 0, 0, 0], "count": 255, "sum": 13179}, {"date": "20220922", "label": "", "histogram": [1656, 13381, 8, 182, 0, 0, 0, 0, 0, 0, 0, 0, 0, 0, 0, 0, 0], "count": 260, "sum": 13943}, {"date": "20220923", "label": "", "histogram": [1766, 10823, 34, 9, 0, 0, 0, 0, 0, 0, 0, 0, 0, 0, 0, 0, 0], "count": 204, "sum": 10918}, {"date": "20220924", "label": "", "histogram": [1525, 7527, 2, 0, 0, 0, 0, 0, 0, 0, 0, 0, 0, 0, 0, 0, 0], "count": 161, "sum": 7531}, {"date": "20220925", "label": "", "histogram": [1660, 9992, 5, 201, 0, 0, 0, 0, 0, 0, 0, 0, 0, 0, 0, 0, 0], "count": 169, "sum": 10605}, {"date": "20220926", "label": "", "histogram": [1919, 11888, 12, 0, 0, 0, 0, 0, 0, 0, 0, 0, 0, 0, 0, 0, 0], "count": 222, "sum": 11912}, {"date": "20220927", "label": "", "histogram": [2815, 13028, 28, 0, 0, 0, 0, 0, 0, 0, 0, 0, 0, 0, 0, 0, 0], "count": 220, "sum": 13084}, {"date": "20220928", "label": "", "histogram": [1800, 10146, 17, 0, 0, 0, 0, 0, 0, 0, 0, 0, 0, 0, 0, 0, 0], "count": 217, "sum": 10180}, {"date": "20220929", "label": "", "histogram": [3495, 12333, 50, 518, 0, 0, 0, 0, 0, 0, 0, 0, 0, 0, 0, 0, 0], "count": 234, "sum": 13987}, {"date": "20220930", "label": "", "histogram": [1986, 10706, 85, 66, 0, 0, 0, 0, 0, 0, 0, 0, 0, 0, 0, 0, 0], "count": 206, "sum": 11074}, {"date": "20221001", "label": "", "histogram": [2030, 8771, 39, 262, 0, 0, 0, 0, 0, 0, 0, 0, 0, 0, 0, 0, 0], "count": 156, "sum": 9635}, {"date": "20221002", "label": "", "histogram": [891, 9743, 4, 601, 0, 0, 0, 0, 0, 0, 0, 0, 0, 0, 0, 0, 0], "count": 159, "sum": 11554}, {"date": "20221003", "label": "", "histogram": [7574, 10159, 19, 412, 0, 0, 0, 0, 0, 0, 0, 0, 0, 0, 0, 0, 0], "count": 196, "sum": 11433}, {"date": "20221004", "label": "", "histogram": [796, 11253, 53, 415, 0, 0, 0, 0, 0, 0, 0, 0, 0, 0, 0, 0, 0], "count": 201, "sum": 12604}, {"date": "20221005", "label": "", "histogram": [1333, 9699, 12, 487, 0, 0, 0, 0, 0, 0, 0, 0, 0, 0, 0, 0, 0], "count": 196, "sum": 11184}, {"date": "20221006", "label": "", "histogram": [736, 8051, 19, 1364, 0, 0, 0, 0, 0, 0, 0, 0, 0, 0, 0, 0, 0], "count": 195, "sum": 12181}, {"date": "20221007", "label": "", "histogram": [839, 7879, 20, 900, 0, 0, 0, 0, 0, 0, 0, 0, 0, 0, 0, 0, 0], "count": 210, "sum": 10619}, {"date": "20221008", "label": "", "histogram": [474, 6140, 5, 328, 0, 0, 0, 0, 0, 0, 0, 0, 0, 0, 0, 0, 0], "count": 118, "sum": 7134}, {"date": "20221009", "label": "", "histogram": [328, 6401, 34, 218, 0, 0, 0, 0, 0, 0, 0, 0, 0, 0, 0, 0, 0], "count": 141, "sum": 7123}, {"date": "20221010", "label": "", "histogram": [821, 7780, 80, 205, 0, 0, 0, 0, 0, 0, 0, 0, 0, 0, 0, 0, 0], "count": 171, "sum": 8555}, {"date": "20221011", "label": "", "histogram": [2126, 9562, 85, 532, 0, 0, 0, 0, 0, 0, 0, 0, 0, 0, 0, 0, 0], "count": 239, "sum": 11328}, {"date": "20221012", "label": "", "histogram": [864, 9875, 14, 2180, 0, 0, 0, 0, 0, 0, 0, 0, 0, 0, 0, 0, 0], "count": 217, "sum": 16443}, {"date": "20221013", "label": "", "histogram": [725, 9068, 78, 1763, 0, 0, 0, 0, 0, 0, 0, 0, 0, 0, 0, 0, 0], "count": 197, "sum": 14513}, {"date": "20221014", "label": "", "histogram": [672, 7694, 23, 2901, 0, 0, 0, 0, 0, 0, 0, 0, 0, 0, 0, 0, 0], "count": 170, "sum": 16443}, {"date": "20221015", "label": "", "histogram": [887, 8305, 16, 0, 0, 0, 0, 0, 0, 0, 0, 0, 0, 0, 0, 0, 0], "count": 148, "sum": 8337}, {"date": "20221016", "label": "", "histogram": [252, 7290, 89, 212, 0, 0, 0, 0, 0, 0, 0, 0, 0, 0, 0, 0, 0], "count": 136, "sum": 8104}, {"date": "20221017", "label": "", "histogram": [1018, 11090, 93, 536, 0, 0, 0, 0, 0, 0, 0, 0, 0, 0, 0, 0, 0], "count": 188, "sum": 12884}, {"date": "20221018", "label": "", "histogram": [2258, 9492, 458, 452, 0, 0, 0, 0, 0, 0, 0, 0, 0, 0, 0, 0, 0], "count": 182, "sum": 11764}, {"date": "20221019", "label": "", "histogram": [1082, 10162, 44, 847, 0, 0, 0, 0, 0, 0, 0, 0, 0, 0, 0, 0, 0], "count": 220, "sum": 12791}, {"date": "20221020", "label": "", "histogram": [827, 9106, 279, 847, 0, 0, 0, 0, 0, 0, 0, 0, 0, 0, 0, 0, 0], "count": 217, "sum": 12205}, {"date": "20221021", "label": "", "histogram": [1065, 10075, 103, 662, 0, 0, 0, 0, 0, 0, 0, 0, 0, 0, 0, 0, 0], "count": 227, "sum": 12267}, {"date": "20221022", "label": "", "histogram": [538, 8477, 1, 220, 0, 0, 0, 0, 0, 0, 0, 0, 0, 0, 0, 0, 0], "count": 147, "sum": 9139}, {"date": "20221023", "label": "", "histogram": [393, 6298, 21, 225, 0, 0, 0, 0, 0, 0, 0, 0, 0, 0, 0, 0, 0], "count": 112, "sum": 7015}, {"date": "20221024", "label": "", "histogram": [999, 7930, 91, 985, 0, 0, 0, 0, 0, 0, 0, 0, 0, 0, 0, 0, 0], "count": 170, "sum": 11067}, {"date": "20221025", "label": "", "histogram": [890, 9024, 108, 570, 0, 0, 0, 0, 0, 0, 0, 0, 0, 0, 0, 0, 0], "count": 195, "sum": 10950}, {"date": "20221026", "label": "", "histogram": [1375, 10212, 150, 1210, 0, 0, 0, 0, 0, 0, 0, 0, 0, 0, 0, 0, 0], "count": 202, "sum": 14142}, {"date": "20221027", "label": "", "histogram": [3829, 12793, 175, 110, 0, 0, 0, 0, 0, 0, 0, 0, 0, 0, 0, 0, 0], "count": 218, "sum": 13473}, {"date": "20221028", "label": "", "histogram": [906, 9882, 182, 415, 0, 0, 0, 0, 0, 0, 0, 0, 0, 0, 0, 0, 0], "count": 190, "sum": 11491}, {"date": "20221029", "label": "", "histogram": [928, 7315, 6, 308, 0, 0, 0, 0, 0, 0, 0, 0, 0, 0, 0, 0, 0], "count": 133, "sum": 8251}, {"date": "20221030", "label": "", "histogram": [1469, 8374, 11, 234, 0, 0, 0, 0, 0, 0, 0, 0, 0, 0, 0, 0, 0], "count": 125, "sum": 9098}, {"date": "20221031", "label": "", "histogram": [2478, 10245, 30, 272, 0, 0, 0, 0, 0, 0, 0, 0, 0, 0, 0, 0, 0], "count": 202, "sum": 11121}, {"date": "20221101", "label": "", "histogram": [1139, 10205, 212, 251, 0, 0, 0, 0, 0, 0, 0, 0, 0, 0, 0, 0, 0], "count": 186, "sum": 11382}, {"date": "20221102", "label": "", "histogram": [1090, 9137, 185, 214, 0, 0, 0, 0, 0, 0, 0, 0, 0, 0, 0, 0, 0], "count": 175, "sum": 10149}, {"date": "20221103", "label": "", "histogram": [1918, 11077, 197, 250, 0, 0, 0, 0, 0, 0, 0, 0, 0, 0, 0, 0, 0], "count": 224, "sum": 12221}, {"date": "20221104", "label": "", "histogram": [400, 10630, 21, 299, 0, 0, 0, 0, 0, 0, 0, 0, 0, 0, 0, 0, 0], "count": 197, "sum": 11569}, {"date": "20221105", "label": "", "histogram": [280, 8086, 9, 604, 0, 0, 0, 0, 0, 0, 0, 0, 0, 0, 0, 0, 0], "count": 189, "sum": 9916}, {"date": "20221106", "label": "", "histogram": [410, 7764, 2, 215, 0, 0, 0, 0, 0, 0, 0, 0, 0, 0, 0, 0, 0], "count": 126, "sum": 8413}, {"date": "20221107", "label": "", "histogram": [693, 10828, 421, 211, 0, 0, 0, 0, 0, 0, 0, 0, 0, 0, 0, 0, 0], "count": 207, "sum": 12303}, {"date": "20221108", "label": "", "histogram": [817, 7566, 170, 179, 0, 0, 0, 0, 0, 0, 0, 0, 0, 0, 0, 0, 0], "count": 149, "sum": 8443}, {"date": "20221109", "label": "", "histogram": [919, 11849, 251, 199, 0, 0, 0, 0, 0, 0, 0, 0, 0, 0, 0, 0, 0], "count": 203, "sum": 12948}, {"date": "20221110", "label": "", "histogram": [789, 11582, 10, 297, 0, 0, 0, 0, 0, 0, 0, 0, 0, 0, 0, 0, 0], "count": 199, "sum": 12493}, {"date": "20221111", "label": "", "histogram": [676, 7346, 19, 213, 0, 0, 0, 0, 0, 0, 0, 0, 0, 0, 0, 0, 0], "count": 151, "sum": 8023}, {"date": "20221112", "label": "", "histogram": [145, 6219, 8, 237, 0, 0, 0, 0, 0, 0, 0, 0, 0, 0, 0, 0, 0], "count": 96, "sum": 6946}, {"date": "20221113", "label": "", "histogram": [504, 8569, 12, 229, 0, 0, 0, 0, 0, 0, 0, 0, 0, 0, 0, 0, 0], "count": 106, "sum": 9280}, {"date": "20221114", "label": "", "histogram": [806, 11921, 26, 99, 0, 0, 0, 0, 0, 0, 0, 0, 0, 0, 0, 0, 0], "count": 168, "sum": 12270}, {"date": "20221115", "label": "", "histogram": [850, 7174, 28, 177, 0, 0, 0, 0, 0, 0, 0, 0, 0, 0, 0, 0, 0], "count": 157, "sum": 7761}, {"date": "20221116", "label": "", "histogram": [1297, 10932, 24, 183, 0, 0, 0, 0, 0, 0, 0, 0, 0, 0, 0, 0, 0], "count": 181, "sum": 11529}, {"date": "20221117", "label": "", "histogram": [1233, 12939, 50, 207, 0, 0, 0, 0, 0, 0, 0, 0, 0, 0, 0, 0, 0], "count": 194, "sum": 13660}, {"date": "20221118", "label": "", "histogram": [1263, 9116, 24, 156, 0, 0, 0, 0, 0, 0, 0, 0, 0, 0, 0, 0, 0], "count": 138, "sum": 9632}, {"date": "20221119", "label": "", "histogram": [779, 5338, 1, 0, 0, 0, 0, 0, 0, 0, 0, 0, 0, 0, 0, 0, 0], "count": 79, "sum": 5340}, {"date": "20221120", "label": "", "histogram": [1767, 7880, 7, 45, 0, 0, 0, 0, 0, 0, 0, 0, 0, 0, 0, 0, 0], "count": 96, "sum": 8029}, {"date": "20221121", "label": "", "histogram": [2147, 9065, 253, 760, 0, 0, 0, 0, 0, 0, 0, 0, 0, 0, 0, 0, 0], "count": 150, "sum": 11851}, {"date": "20221122", "label": "", "histogram": [1550, 6886, 22, 168, 0, 0, 0, 0, 0, 0, 0, 0, 0, 0, 0, 0, 0], "count": 135, "sum": 7434}, {"date": "20221123", "label": "", "histogram": [2236, 6427, 30, 436, 0, 0, 0, 0, 0, 0, 0, 0, 0, 0, 0, 0, 0], "count": 165, "sum": 7795}, {"date": "20221124", "label": "", "histogram": [5681, 7168, 118, 169, 0, 0, 0, 0, 0, 0, 0, 0, 0, 0, 0, 0, 0], "count": 158, "sum": 7911}, {"date": "20221125", "label": "", "histogram": [1714, 6247, 332, 0, 0, 0, 0, 0, 0, 0, 0, 0, 0, 0, 0, 0, 0], "count": 131, "sum": 6911}, {"date": "20221126", "label": "", "histogram": [1267, 8746, 5, 1, 0, 0, 0, 0, 0, 0, 0, 0, 0, 0, 0, 0, 0], "count": 106, "sum": 8759}, {"date": "20221127", "label": "", "histogram": [344, 4782, 11, 1, 0, 0, 0, 0, 0, 0, 0, 0, 0, 0, 0, 0, 0], "count": 89, "sum": 4807}, {"date": "20221128", "label": "", "histogram": [1624, 9060, 133, 6316, 0, 0, 0, 0, 0, 0, 0, 0, 0, 0, 0, 0, 0], "count": 159, "sum": 28274}, {"date": "20221129", "label": "", "histogram": [1367, 6551, 13, 8, 0, 0, 0, 0, 0, 0, 0, 0, 0, 0, 0, 0, 0], "count": 145, "sum": 6601}, {"date": "20221130", "label": "", "histogram": [2871, 9041, 180, 2894, 0, 0, 0, 0, 0, 0, 0, 0, 0, 0, 0, 0, 0], "count": 177, "sum": 18083}, {"date": "20221201", "label": "", "histogram": [662, 6374, 195, 1238, 0, 0, 0, 0, 0, 0, 0, 0, 0, 0, 0, 0, 0], "count": 160, "sum": 10478}, {"date": "20221202", "label": "", "histogram": [997, 10257, 174, 127, 0, 0, 0, 0, 0, 0, 0, 0, 0, 0, 0, 0, 0], "count": 183, "sum": 10986}, {"date": "20221203", "label": "", "histogram": [636, 9674, 9, 360, 0, 0, 0, 0, 0, 0, 0, 0, 0, 0, 0, 0, 0], "count": 104, "sum": 10772}, {"date": "20221204", "label": "", "histogram": [628, 8168, 4, 339, 0, 0, 0, 0, 0, 0, 0, 0, 0, 0, 0, 0, 0], "count": 113, "sum": 9193}, {"date": "20221205", "label": "", "histogram": [1080, 9253, 96, 328, 0, 0, 0, 0, 0, 0, 0, 0, 0, 0, 0, 0, 0], "count": 182, "sum": 10429}, {"date": "20221206", "label": "", "histogram": [3582, 12617, 41, 71, 0, 0, 0, 0, 0, 0, 0, 0, 0, 0, 0, 0, 0], "count": 171, "sum": 12912}, {"date": "20221207", "label": "", "histogram": [1757, 12910, 116, 336, 0, 0, 0, 0, 0, 0, 0, 0, 0, 0, 0, 0, 0], "count": 169, "sum": 14150}, {"date": "20221208", "label": "", "histogram": [1294, 5886, 45, 115, 0, 0, 0, 0, 0, 0, 0, 0, 0, 0, 0, 0, 0], "count": 134, "sum": 6321}, {"date": "20221209", "label": "", "histogram": [848, 6192, 2, 256, 0, 0, 0, 0, 0, 0, 0, 0, 0, 0, 0, 0, 0], "count": 120, "sum": 6964}, {"date": "20221210", "label": "", "histogram": [1277, 9812, 8, 248, 0, 0, 0, 0, 0, 0, 0, 0, 0, 0, 0, 0, 0], "count": 88, "sum": 10572}, {"date": "20221211", "label": "", "histogram": [1354, 8467, 7, 205, 0, 0, 0, 0, 0, 0, 0, 0, 0, 0, 0, 0, 0], "count": 103, "sum": 9096}, {"date": "20221212", "label": "", "histogram": [969, 8322, 131, 4, 0, 0, 0, 0, 0, 0, 0, 0, 0, 0, 0, 0, 0], "count": 144, "sum": 8596}, {"date": "20221213", "label": "", "histogram": [1640, 8952, 29, 63, 0, 0, 0, 0, 0, 0, 0, 0, 0, 0, 0, 0, 0], "count": 148, "sum": 9199}, {"date": "20221214", "label": "", "histogram": [879, 8565, 53, 364, 0, 0, 0, 0, 0, 0, 0, 0, 0, 0, 0, 0, 0], "count": 128, "sum": 9763}, {"date": "20221215", "label": "", "histogram": [1423, 7181, 5, 573, 0, 0, 0, 0, 0, 0, 0, 0, 0, 0, 0, 0, 0], "count": 148, "sum": 8910}, {"date": "20221216", "label": "", "histogram": [1083, 10939, 37, 536, 0, 0, 0, 0, 0, 0, 0, 0, 0, 0, 0, 0, 0], "count": 121, "sum": 12621}, {"date": "20221217", "label": "", "histogram": [1407, 8517, 9, 415, 0, 0, 0, 0, 0, 0, 0, 0, 0, 0, 0, 0, 0], "count": 129, "sum": 9780}, {"date": "20221218", "label": "", "histogram": [1389, 8034, 40, 357, 0, 0, 0, 0, 0, 0, 0, 0, 0, 0, 0, 0, 0], "count": 104, "sum": 9185}, {"date": "20221219", "label": "", "histogram": [1336, 7737, 295, 0, 0, 0, 0, 0, 0, 0, 0, 0, 0, 0, 0, 0, 0], "count": 96, "sum": 8327}, {"date": "20221220", "label": "", "histogram": [913, 6863, 153, 336, 0, 0, 0, 0, 0, 0, 0, 0, 0, 0, 0, 0, 0], "count": 107, "sum": 8177}, {"date": "20221221", "label": "", "histogram": [670, 7756, 452, 233, 0, 0, 0, 0, 0, 0, 0, 0, 0, 0, 0, 0, 0], "count": 96, "sum": 9359}, {"date": "20221222", "label": "", "histogram": [590, 6162, 148, 2, 0, 0, 0, 0, 0, 0, 0, 0, 0, 0, 0, 0, 0], "count": 99, "sum": 6464}, {"date": "20221223", "label": "", "histogram": [572, 5719, 140, 0, 0, 0, 0, 0, 0, 0, 0, 0, 0, 0, 0, 0, 0], "count": 80, "sum": 5999}, {"date": "20221224", "label": "", "histogram": [1507, 5940, 135, 392, 0, 0, 0, 0, 0, 0, 0, 0, 0, 0, 0, 0, 0], "count": 71, "sum": 7386}, {"date": "20221225", "label": "", "histogram": [447, 4365, 136, 235, 0, 0, 0, 0, 0, 0, 0, 0, 0, 0, 0, 0, 0], "count": 78, "sum": 5342}, {"date": "20221226", "label": "", "histogram": [447, 4239, 176, 65, 0, 0, 0, 0, 0, 0, 0, 0, 0, 0, 0, 0, 0], "count": 79, "sum": 4786}, {"date": "20221227", "label": "", "histogram": [623, 5156, 141, 203, 0, 0, 0, 0, 0, 0, 0, 0, 0, 0, 0, 0, 0], "count": 110, "sum": 6047}, {"date": "20221228", "label": "", "histogram": [674, 5449, 148, 178, 0, 0, 0, 0, 0, 0, 0, 0, 0, 0, 0, 0, 0], "count": 78, "sum": 6279}, {"date": "20221229", "label": "", "histogram": [896, 3969, 135, 0, 0, 0, 0, 0, 0, 0, 0, 0, 0, 0, 0, 0, 0], "count": 78, "sum": 4239}, {"date": "20221230", "label": "", "histogram": [1345, 3406, 145, 1, 0, 0, 0, 0, 0, 0, 0, 0, 0, 0, 0, 0, 0], "count": 66, "sum": 3699}, {"date": "20221231", "label": "", "histogram": [615, 2679, 120, 2, 0, 0, 0, 0, 0, 0, 0, 0, 0, 0, 0, 0, 0], "count": 50, "sum": 2925}, {"date": "20230101", "label": "", "histogram": [57, 2411, 121, 0, 0, 0, 0, 0, 0, 0, 0, 0, 0, 0, 0, 0, 0], "count": 57, "sum": 2653}, {"date": "20230102", "label": "", "histogram": [1162, 3631, 119, 0, 0, 0, 0, 0, 0, 0, 0, 0, 0, 0, 0, 0, 0], "count": 72, "sum": 3869}, {"date": "20230103", "label": "", "histogram": [1011, 4020, 270, 353, 0, 0, 0, 0, 0, 0, 0, 0, 0, 0, 0, 0, 0], "count": 120, "sum": 5619}, {"date": "20230104", "label": "", "histogram": [234, 3950, 298, 839, 0, 0, 0, 0, 0, 0, 0, 0, 0, 0, 0, 0, 0], "count": 94, "sum": 7063}, {"date": "20230105", "label": "", "histogram": [329, 5057, 194, 401, 0, 0, 0, 0, 0, 0, 0, 0, 0, 0, 0, 0, 0], "count": 112, "sum": 6648}, {"date": "20230106", "label": "", "histogram": [506, 4459, 171, 882, 0, 0, 0, 0, 0, 0, 0, 0, 0, 0, 0, 0, 0], "count": 119, "sum": 7447}, {"date": "20230107", "label": "", "histogram": [254, 4137, 156, 0, 0, 0, 0, 0, 0, 0, 0, 0, 0, 0, 0, 0, 0], "count": 85, "sum": 4449}, {"date": "20230108", "label": "", "histogram": [117, 2698, 156, 0, 0, 0, 0, 0, 0, 0, 0, 0, 0, 0, 0, 0, 0], "count": 64, "sum": 3010}, {"date": "20230109", "label": "", "histogram": [505, 6616, 184, 15287, 0, 0, 0, 0, 0, 0, 0, 0, 0, 0, 0, 0, 0], "count": 129, "sum": 52845}, {"date": "20230110", "label": "", "histogram": [1068, 5843, 146, 656, 0, 0, 0, 0, 0, 0, 0, 0, 0, 0, 0, 0, 0], "count": 134, "sum": 8103}, {"date": "20230111", "label": "", "histogram": [1367, 7045, 149, 1067, 0, 0, 0, 0, 0, 0, 0, 0, 0, 0, 0, 0, 0], "count": 161, "sum": 10544}, {"date": "20230112", "label": "", "histogram": [987, 6637, 191, 1341, 0, 0, 0, 0, 0, 0, 0, 0, 0, 0, 0, 0, 0], "count": 134, "sum": 11042}, {"date": "20230113", "label": "", "histogram": [711, 5920, 185, 1345, 0, 0, 0, 0, 0, 0, 0, 0, 0, 0, 0, 0, 0], "count": 121, "sum": 10325}, {"date": "20230114", "label": "", "histogram": [703, 6256, 150, 1, 0, 0, 0, 0, 0, 0, 0, 0, 0, 0, 0, 0, 0], "count": 79, "sum": 6559}, {"date": "20230115", "label": "", "histogram": [495, 4340, 140, 18, 0, 0, 0, 0, 0, 0, 0, 0, 0, 0, 0, 0, 0], "count": 77, "sum": 4674}, {"date": "20230116", "label": "", "histogram": [1059, 4765, 163, 0, 0, 0, 0, 0, 0, 0, 0, 0, 0, 0, 0, 0, 0], "count": 84, "sum": 5091}, {"date": "20230117", "label": "", "histogram": [533, 4676, 96, 8380, 0, 0, 0, 0, 0, 0, 0, 0, 0, 0, 0, 0, 0], "count": 128, "sum": 30008}, {"date": "20230118", "label": "", "histogram": [363, 3789, 16, 737, 0, 0, 0, 0, 0, 0, 0, 0, 0, 0, 0, 0, 0], "count": 96, "sum": 6032}, {"date": "20230119", "label": "", "histogram": [243, 4536, 52, 482, 0, 0, 0, 0, 0, 0, 0, 0, 0, 0, 0, 0, 0], "count": 115, "sum": 6086}, {"date": "20230120", "label": "", "histogram": [418, 3674, 2, 337, 0, 0, 0, 0, 0, 0, 0, 0, 0, 0, 0, 0, 0], "count": 90, "sum": 4689}, {"date": "20230121", "label": "", "histogram": [762, 4125, 4, 0, 0, 0, 0, 0, 0, 0, 0, 0, 0, 0, 0, 0, 0], "count": 82, "sum": 4133}, {"date": "20230122", "label": "", "histogram": [1963, 3782, 0, 0, 0, 0, 0, 0, 0, 0, 0, 0, 0, 0, 0, 0, 0], "count": 79, "sum": 3782}, {"date": "20230123", "label": "", "histogram": [792, 4589, 2, 9916, 0, 0, 0, 0, 0, 0, 0, 0, 0, 0, 0, 0, 0], "count": 106, "sum": 34341}, {"date": "20230124", "label": "", "histogram": [611, 5187, 4, 759, 0, 0, 0, 0, 0, 0, 0, 0, 0, 0, 0, 0, 0], "count": 92, "sum": 7472}, {"date": "20230125", "label": "", "histogram": [1262, 5486, 7, 225, 0, 0, 0, 0, 0, 0, 0, 0, 0, 0, 0, 0, 0], "count": 115, "sum": 6175}, {"date": "20230126", "label": "", "histogram": [438, 4974, 166, 1001, 0, 0, 0, 0, 0, 0, 0, 0, 0, 0, 0, 0, 0], "count": 125, "sum": 8309}, {"date": "20230127", "label": "", "histogram": [700, 5453, 166, 1562, 0, 0, 0, 0, 0, 0, 0, 0, 0, 0, 0, 0, 0], "count": 104, "sum": 10471}, {"date": "20230128", "label": "", "histogram": [161, 3485, 136, 456, 0, 0, 0, 0, 0, 0, 0, 0, 0, 0, 0, 0, 0], "count": 66, "sum": 5125}, {"date": "20230129", "label": "", "histogram": [222, 3983, 145, 553, 0, 0, 0, 0, 0, 0, 0, 0, 0, 0, 0, 0, 0], "count": 68, "sum": 5932}, {"date": "20230130", "label": "", "histogram": [623, 3799, 140, 132, 0, 0, 0, 0, 0, 0, 0, 0, 0, 0, 0, 0, 0], "count": 112, "sum": 4475}, {"date": "20230131", "label": "", "histogram": [821, 3917, 89, 587, 0, 0, 0, 0, 0, 0, 0, 0, 0, 0, 0, 0, 0], "count": 105, "sum": 5856}, {"date": "20230201", "label": "", "histogram": [1982, 3563, 41, 395, 0, 0, 0, 0, 0, 0, 0, 0, 0, 0, 0, 0, 0], "count": 133, "sum": 4830}, {"date": "20230202", "label": "", "histogram": [975, 4573, 34, 1363, 0, 0, 0, 0, 0, 0, 0, 0, 0, 0, 0, 0, 0], "count": 123, "sum": 8730}, {"date": "20230203", "label": "", "histogram": [665, 4395, 1, 850, 0, 0, 0, 0, 0, 0, 0, 0, 0, 0, 0, 0, 0], "count": 98, "sum": 6947}, {"date": "20230204", "label": "", "histogram": [238, 3201, 7, 918, 0, 0, 0, 0, 0, 0, 0, 0, 0, 0, 0, 0, 0], "count": 60, "sum": 5969}, {"date": "20230205", "label": "", "histogram": [1003, 4727, 12, 1127, 0, 0, 0, 0, 0, 0, 0, 0, 0, 0, 0, 0, 0], "count": 78, "sum": 8132}, {"date": "20230206", "label": "", "histogram": [720, 3647, 20, 770, 0, 0, 0, 0, 0, 0, 0, 0, 0, 0, 0, 0, 0], "count": 67, "sum": 5997}, {"date": "20230207", "label": "", "histogram": [352, 5268, 56, 1196, 0, 0, 0, 0, 0, 0, 0, 0, 0, 0, 0, 0, 0], "count": 104, "sum": 8968}, {"date": "20230208", "label": "", "histogram": [381, 4240, 37, 982, 0, 0, 0, 0, 0, 0, 0, 0, 0, 0, 0, 0, 0], "count": 91, "sum": 7260}, {"date": "20230209", "label": "", "histogram": [577, 3813, 6, 973, 0, 0, 0, 0, 0, 0, 0, 0, 0, 0, 0, 0, 0], "count": 105, "sum": 6744}, {"date": "20230210", "label": "", "histogram": [594, 3304, 58, 997, 0, 0, 0, 0, 0, 0, 0, 0, 0, 0, 0, 0, 0], "count": 103, "sum": 6411}, {"date": "20230211", "label": "", "histogram": [419, 3625, 20, 1789, 0, 0, 0, 0, 0, 0, 0, 0, 0, 0, 0, 0, 0], "count": 49, "sum": 9032}, {"date": "20230212", "label": "", "histogram": [263, 3995, 1, 487, 0, 0, 0, 0, 0, 0, 0, 0, 0, 0, 0, 0, 0], "count": 56, "sum": 5458}, {"date": "20230213", "label": "", "histogram": [746, 4550, 2, 1803, 0, 0, 0, 0, 0, 0, 0, 0, 0, 0, 0, 0, 0], "count": 111, "sum": 9963}, {"date": "20230214", "label": "", "histogram": [2905, 3646, 184, 2166, 0, 0, 0, 0, 0, 0, 0, 0, 0, 0, 0, 0, 0], "count": 119, "sum": 10512}, {"date": "20230215", "label": "", "histogram": [671, 4839, 58, 878, 0, 0, 0, 0, 0, 0, 0, 0, 0, 0, 0, 0, 0], "count": 113, "sum": 7589}, {"date": "20230216", "label": "", "histogram": [718, 4458, 2, 993, 0, 0, 0, 0, 0, 0, 0, 0, 0, 0, 0, 0, 0], "count": 119, "sum": 7441}, {"date": "20230217", "label": "", "histogram": [474, 5634, 76, 441, 0, 0, 0, 0, 0, 0, 0, 0, 0, 0, 0, 0, 0], "count": 160, "sum": 7109}, {"date": "20230218", "label": "", "histogram": [58, 2980, 0, 1247, 0, 0, 0, 0, 0, 0, 0, 0, 0, 0, 0, 0, 0], "count": 48, "sum": 6721}, {"date": "20230219", "label": "", "histogram": [750, 3295, 3, 379, 0, 0, 0, 0, 0, 0, 0, 0, 0, 0, 0, 0, 0], "count": 59, "sum": 4438}, {"date": "20230220", "label": "", "histogram": [896, 4375, 64, 652, 0, 0, 0, 0, 0, 0, 0, 0, 0, 0, 0, 0, 0], "count": 90, "sum": 6459}, {"date": "20230221", "label": "", "histogram": [484, 3953, 90, 462, 0, 0, 0, 0, 0, 0, 0, 0, 0, 0, 0, 0, 0], "count": 139, "sum": 5519}, {"date": "20230222", "label": "", "histogram": [866, 6091, 80, 563, 0, 0, 0, 0, 0, 0, 0, 0, 0, 0, 0, 0, 0], "count": 173, "sum": 7940}, {"date": "20230223", "label": "", "histogram": [601, 5024, 71, 1398, 0, 0, 0, 0, 0, 0, 0, 0, 0, 0, 0, 0, 0], "count": 164, "sum": 9360}, {"date": "20230224", "label": "", "histogram": [679, 5247, 11, 1966, 0, 0, 0, 0, 0, 0, 0, 0, 0, 0, 0, 0, 0], "count": 158, "sum": 11167}, {"date": "20230225", "label": "", "histogram": [155, 4442, 3, 974, 0, 0, 0, 0, 0, 0, 0, 0, 0, 0, 0, 0, 0], "count": 58, "sum": 7370}, {"date": "20211207", "label": "", "histogram": [156144, 2482313, 7335, 90357, 0, 0, 0, 0, 0, 0, 0, 0, 0, 0, 0, 0, 0], "count": 52020, "sum": 2768054}, {"date": "20211208", "label": "", "histogram": [347623, 4659626, 17859, 243382, 0, 0, 0, 0, 0, 0, 0, 0, 0, 0, 0, 0, 0], "count": 81549, "sum": 5425490}, {"date": "20211209", "label": "", "histogram": [413361, 5297198, 18948, 247033, 0, 0, 0, 0, 0, 0, 0, 0, 0, 0, 0, 0, 0], "count": 87650, "sum": 6076193}, {"date": "20211210", "label": "", "histogram": [316461, 5122171, 18835, 264395, 0, 0, 0, 0, 0, 0, 0, 0, 0, 0, 0, 0, 0], "count": 89185, "sum": 5953026}, {"date": "20211211", "label": "", "histogram": [303878, 4488692, 15212, 216572, 0, 0, 0, 0, 0, 0, 0, 0, 0, 0, 0, 0, 0], "count": 80228, "sum": 5168832}, {"date": "20211212", "label": "", "histogram": [282392, 4505960, 15317, 235075, 0, 0, 0, 0, 0, 0, 0, 0, 0, 0, 0, 0, 0], "count": 79618, "sum": 5241819}, {"date": "20211213", "label": "", "histogram": [390983, 5336292, 16156, 273261, 0, 0, 0, 0, 0, 0, 0, 0, 0, 0, 0, 0, 0], "count": 94190, "sum": 6188387}, {"date": "20211214", "label": "", "histogram": [309636, 3020253, 15600, 168280, 0, 0, 0, 0, 0, 0, 0, 0, 0, 0, 0, 0, 0], "count": 53971, "sum": 3556293}, {"date": "20211215", "label": "", "histogram": [626993, 6018441, 27770, 304632, 0, 0, 0, 0, 0, 0, 0, 0, 0, 0, 0, 0, 0], "count": 100598, "sum": 6987877}, {"date": "20211216", "label": "", "histogram": [585849, 5728483, 29740, 305204, 0, 0, 0, 0, 0, 0, 0, 0, 0, 0, 0, 0, 0], "count": 98500, "sum": 6703575}, {"date": "20211217", "label": "", "histogram": [490204, 5275118, 31176, 305324, 0, 0, 0, 0, 0, 0, 0, 0, 0, 0, 0, 0, 0], "count": 94264, "sum": 6253442}, {"date": "20211218", "label": "", "histogram": [449784, 4648440, 27059, 250896, 0, 0, 0, 0, 0, 0, 0, 0, 0, 0, 0, 0, 0], "count": 83580, "sum": 5455246}, {"date": "20211219", "label": "", "histogram": [440399, 4635027, 25158, 265545, 0, 0, 0, 0, 0, 0, 0, 0, 0, 0, 0, 0, 0], "count": 82416, "sum": 5481978}, {"date": "20211220", "label": "", "histogram": [456906, 5431921, 20896, 306410, 0, 0, 0, 0, 0, 0, 0, 0, 0, 0, 0, 0, 0], "count": 96176, "sum": 6392943}, {"date": "20211221", "label": "", "histogram": [486902, 5681299, 18719, 355441, 0, 0, 0, 0, 0, 0, 0, 0, 0, 0, 0, 0, 0], "count": 102032, "sum": 6785060}, {"date": "20211222", "label": "", "histogram": [514444, 4989881, 22765, 284563, 0, 0, 0, 0, 0, 0, 0, 0, 0, 0, 0, 0, 0], "count": 98435, "sum": 5889100}, {"date": "20211223", "label": "", "histogram": [425764, 5038032, 18416, 273260, 0, 0, 0, 0, 0, 0, 0, 0, 0, 0, 0, 0, 0], "count": 91695, "sum": 5894644}, {"date": "20211224", "label": "", "histogram": [349943, 4489840, 16934, 257384, 0, 0, 0, 0, 0, 0, 0, 0, 0, 0, 0, 0, 0], "count": 83373, "sum": 5295860}, {"date": "20211225", "label": "", "histogram": [375214, 4017725, 12965, 214519, 0, 0, 0, 0, 0, 0, 0, 0, 0, 0, 0, 0, 0], "count": 74524, "sum": 4687212}, {"date": "20211226", "label": "", "histogram": [516359, 4313189, 28563, 231923, 0, 0, 0, 0, 0, 0, 0, 0, 0, 0, 0, 0, 0], "count": 76600, "sum": 5066084}, {"date": "20211227", "label": "", "histogram": [500092, 5123798, 27341, 272473, 0, 0, 0, 0, 0, 0, 0, 0, 0, 0, 0, 0, 0], "count": 91470, "sum": 5995899}, {"date": "20211228", "label": "", "histogram": [461520, 5589704, 23720, 338313, 0, 0, 0, 0, 0, 0, 0, 0, 0, 0, 0, 0, 0], "count": 91921, "sum": 6652083}, {"date": "20211229", "label": "", "histogram": [779700, 5872044, 22915, 314025, 0, 0, 0, 0, 0, 0, 0, 0, 0, 0, 0, 0, 0], "count": 93559, "sum": 6859949}, {"date": "20211230", "label": "", "histogram": [507016, 5429307, 22436, 292208, 0, 0, 0, 0, 0, 0, 0, 0, 0, 0, 0, 0, 0], "count": 92466, "sum": 6350803}, {"date": "20211231", "label": "", "histogram": [511078, 4517434, 17651, 247740, 0, 0, 0, 0, 0, 0, 0, 0, 0, 0, 0, 0, 0], "count": 82687, "sum": 5295956}, {"date": "20220101", "label": "", "histogram": [329341, 4442907, 15025, 223974, 0, 0, 0, 0, 0, 0, 0, 0, 0, 0, 0, 0, 0], "count": 75942, "sum": 5144879}, {"date": "20220102", "label": "", "histogram": [484886, 5447759, 19082, 259641, 0, 0, 0, 0, 0, 0, 0, 0, 0, 0, 0, 0, 0], "count": 80224, "sum": 6264846}, {"date": "20220103", "label": "", "histogram": [744663, 6049365, 26392, 309669, 0, 0, 0, 0, 0, 0, 0, 0, 0, 0, 0, 0, 0], "count": 97183, "sum": 7031156}, {"date": "20220104", "label": "", "histogram": [512853, 6371898, 26352, 333685, 0, 0, 0, 0, 0, 0, 0, 0, 0, 0, 0, 0, 0], "count": 112237, "sum": 7425657}, {"date": "20220105", "label": "", "histogram": [508774, 6046787, 22949, 324558, 0, 0, 0, 0, 0, 0, 0, 0, 0, 0, 0, 0, 0], "count": 102595, "sum": 7066359}, {"date": "20220106", "label": "", "histogram": [597251, 5441192, 22516, 320322, 0, 0, 0, 0, 0, 0, 0, 0, 0, 0, 0, 0, 0], "count": 97405, "sum": 6447190}, {"date": "20220107", "label": "", "histogram": [559515, 5544052, 25870, 330197, 0, 0, 0, 0, 0, 0, 0, 0, 0, 0, 0, 0, 0], "count": 97863, "sum": 6586383}, {"date": "20220108", "label": "", "histogram": [753045, 5063641, 14597, 279159, 0, 0, 0, 0, 0, 0, 0, 0, 0, 0, 0, 0, 0], "count": 89331, "sum": 5930312}, {"date": "20220109", "label": "", "histogram": [430674, 4897579, 18125, 276997, 0, 0, 0, 0, 0, 0, 0, 0, 0, 0, 0, 0, 0], "count": 88014, "sum": 5764820}, {"date": "20220110", "label": "", "histogram": [703489, 5937962, 23959, 326377, 0, 0, 0, 0, 0, 0, 0, 0, 0, 0, 0, 0, 0], "count": 105542, "sum": 6965011}, {"date": "20220111", "label": "", "histogram": [527082, 3772108, 20362, 257692, 0, 0, 0, 0, 0, 0, 0, 0, 0, 0, 0, 0, 0], "count": 57074, "sum": 4585908}, {"date": "20220112", "label": "", "histogram": [212933, 1773825, 10641, 158801, 0, 0, 0, 0, 0, 0, 0, 0, 0, 0, 0, 0, 0], "count": 27924, "sum": 2271510}, {"date": "20220113", "label": "", "histogram": [102189, 1181629, 9312, 78907, 0, 0, 0, 0, 0, 0, 0, 0, 0, 0, 0, 0, 0], "count": 21244, "sum": 1436974}, {"date": "20220114", "label": "", "histogram": [125699, 962612, 9435, 82427, 0, 0, 0, 0, 0, 0, 0, 0, 0, 0, 0, 0, 0], "count": 16254, "sum": 1228763}, {"date": "20220115", "label": "", "histogram": [84672, 706651, 3919, 63037, 0, 0, 0, 0, 0, 0, 0, 0, 0, 0, 0, 0, 0], "count": 12953, "sum": 903600}, {"date": "20220116", "label": "", "histogram": [45734, 589234, 2083, 45951, 0, 0, 0, 0, 0, 0, 0, 0, 0, 0, 0, 0, 0], "count": 11063, "sum": 731253}, {"date": "20220117", "label": "", "histogram": [52654, 603220, 12900, 52112, 0, 0, 0, 0, 0, 0, 0, 0, 0, 0, 0, 0, 0], "count": 11671, "sum": 785356}, {"date": "20220118", "label": "", "histogram": [59986, 590224, 8073, 43216, 0, 0, 0, 0, 0, 0, 0, 0, 0, 0, 0, 0, 0], "count": 10706, "sum": 736018}, {"date": "20220119", "label": "", "histogram": [51589, 542924, 2791, 32714, 0, 0, 0, 0, 0, 0, 0, 0, 0, 0, 0, 0, 0], "count": 9462, "sum": 646648}, {"date": "20220120", "label": "", "histogram": [38770, 482479, 2016, 37470, 0, 0, 0, 0, 0, 0, 0, 0, 0, 0, 0, 0, 0], "count": 8350, "sum": 598921}, {"date": "20220121", "label": "", "histogram": [36977, 423520, 2508, 23084, 0, 0, 0, 0, 0, 0, 0, 0, 0, 0, 0, 0, 0], "count": 7379, "sum": 497788}, {"date": "20220122", "label": "", "histogram": [36798, 332499, 1955, 19891, 0, 0, 0, 0, 0, 0, 0, 0, 0, 0, 0, 0, 0], "count": 6265, "sum": 396082}, {"date": "20220123", "label": "", "histogram": [22692, 278634, 3683, 14636, 0, 0, 0, 0, 0, 0, 0, 0, 0, 0, 0, 0, 0], "count": 5382, "sum": 329908}, {"date": "20220124", "label": "", "histogram": [29909, 299807, 2605, 23809, 0, 0, 0, 0, 0, 0, 0, 0, 0, 0, 0, 0, 0], "count": 6133, "sum": 376444}, {"date": "20220125", "label": "", "histogram": [24898, 286227, 3414, 25256, 0, 0, 0, 0, 0, 0, 0, 0, 0, 0, 0, 0, 0], "count": 5726, "sum": 368823}, {"date": "20220126", "label": "", "histogram": [17541, 270362, 3215, 22597, 0, 0, 0, 0, 0, 0, 0, 0, 0, 0, 0, 0, 0], "count": 5334, "sum": 344583}, {"date": "20220127", "label": "", "histogram": [18145, 270031, 2509, 17948, 0, 0, 0, 0, 0, 0, 0, 0, 0, 0, 0, 0, 0], "count": 5124, "sum": 328893}, {"date": "20220128", "label": "", "histogram": [20403, 234650, 3090, 18216, 0, 0, 0, 0, 0, 0, 0, 0, 0, 0, 0, 0, 0], "count": 4648, "sum": 295478}, {"date": "20220129", "label": "", "histogram": [13463, 199497, 1559, 16522, 0, 0, 0, 0, 0, 0, 0, 0, 0, 0, 0, 0, 0], "count": 4069, "sum": 252181}, {"date": "20220130", "label": "", "histogram": [11211, 173965, 469, 9799, 0, 0, 0, 0, 0, 0, 0, 0, 0, 0, 0, 0, 0], "count": 3675, "sum": 204300}, {"date": "20220131", "label": "", "histogram": [13030, 201627, 739, 17048, 0, 0, 0, 0, 0, 0, 0, 0, 0, 0, 0, 0, 0], "count": 4149, "sum": 254249}, {"date": "20220201", "label": "", "histogram": [14924, 200117, 555, 16450, 0, 0, 0, 0, 0, 0, 0, 0, 0, 0, 0, 0, 0], "count": 3970, "sum": 250577}, {"date": "20220202", "label": "", "histogram": [12884, 208837, 829, 15690, 0, 0, 0, 0, 0, 0, 0, 0, 0, 0, 0, 0, 0], "count": 4018, "sum": 257565}, {"date": "20220203", "label": "", "histogram": [11268, 202943, 1186, 17236, 0, 0, 0, 0, 0, 0, 0, 0, 0, 0, 0, 0, 0], "count": 3776, "sum": 257023}, {"date": "20220204", "label": "", "histogram": [14562, 210865, 1156, 14032, 0, 0, 0, 0, 0, 0, 0, 0, 0, 0, 0, 0, 0], "count": 3755, "sum": 255273}, {"date": "20220205", "label": "", "histogram": [9956, 155830, 1010, 14985, 0, 0, 0, 0, 0, 0, 0, 0, 0, 0, 0, 0, 0], "count": 3341, "sum": 202805}, {"date": "20220206", "label": "", "histogram": [17919, 161310, 2327, 15740, 0, 0, 0, 0, 0, 0, 0, 0, 0, 0, 0, 0, 0], "count": 3200, "sum": 213184}, {"date": "20220207", "label": "", "histogram": [10998, 159849, 1410, 15646, 0, 0, 0, 0, 0, 0, 0, 0, 0, 0, 0, 0, 0], "count": 3452, "sum": 209607}, {"date": "20220208", "label": "", "histogram": [12333, 161274, 1119, 11414, 0, 0, 0, 0, 0, 0, 0, 0, 0, 0, 0, 0, 0], "count": 3292, "sum": 197754}, {"date": "20220209", "label": "", "histogram": [12924, 161065, 1903, 15569, 0, 0, 0, 0, 0, 0, 0, 0, 0, 0, 0, 0, 0], "count": 3224, "sum": 211578}, {"date": "20220210", "label": "", "histogram": [12097, 157496, 684, 9412, 0, 0, 0, 0, 0, 0, 0, 0, 0, 0, 0, 0, 0], "count": 3059, "sum": 187100}, {"date": "20220211", "label": "", "histogram": [11726, 145075, 845, 13326, 0, 0, 0, 0, 0, 0, 0, 0, 0, 0, 0, 0, 0], "count": 2997, "sum": 186743}, {"date": "20220212", "label": "", "histogram": [9522, 134395, 597, 9912, 0, 0, 0, 0, 0, 0, 0, 0, 0, 0, 0, 0, 0], "count": 2698, "sum": 165325}, {"date": "20220213", "label": "", "histogram": [6568, 120238, 438, 10867, 0, 0, 0, 0, 0, 0, 0, 0, 0, 0, 0, 0, 0], "count": 2611, "sum": 153715}, {"date": "20220214", "label": "", "histogram": [9545, 128117, 247, 14310, 0, 0, 0, 0, 0, 0, 0, 0, 0, 0, 0, 0, 0], "count": 2711, "sum": 171541}, {"date": "20220215", "label": "", "histogram": [9496, 132173, 718, 13922, 0, 0, 0, 0, 0, 0, 0, 0, 0, 0, 0, 0, 0], "count": 2665, "sum": 175375}, {"date": "20220216", "label": "", "histogram": [9211, 133741, 492, 13135, 0, 0, 0, 0, 0, 0, 0, 0, 0, 0, 0, 0, 0], "count": 2552, "sum": 174130}, {"date": "20220217", "label": "", "histogram": [9803, 125493, 268, 10329, 0, 0, 0, 0, 0, 0, 0, 0, 0, 0, 0, 0, 0], "count": 2425, "sum": 157016}, {"date": "20220218", "label": "", "histogram": [9235, 129880, 523, 8252, 0, 0, 0, 0, 0, 0, 0, 0, 0, 0, 0, 0, 0], "count": 2485, "sum": 155682}, {"date": "20220219", "label": "", "histogram": [6839, 112954, 108, 12021, 0, 0, 0, 0, 0, 0, 0, 0, 0, 0, 0, 0, 0], "count": 2159, "sum": 149233}, {"date": "20220220", "label": "", "histogram": [5967, 98635, 242, 13046, 0, 0, 0, 0, 0, 0, 0, 0, 0, 0, 0, 0, 0], "count": 2119, "sum": 138257}, {"date": "20220221", "label": "", "histogram": [10870, 103635, 391, 7335, 0, 0, 0, 0, 0, 0, 0, 0, 0, 0, 0, 0, 0], "count": 2230, "sum": 126422}, {"date": "20220222", "label": "", "histogram": [9004, 105955, 472, 2737, 0, 0, 0, 0, 0, 0, 0, 0, 0, 0, 0, 0, 0], "count": 2223, "sum": 115110}, {"date": "20220223", "label": "", "histogram": [6348, 98798, 558, 4124, 0, 0, 0, 0, 0, 0, 0, 0, 0, 0, 0, 0, 0], "count": 2048, "sum": 112286}, {"date": "20220224", "label": "", "histogram": [6633, 112719, 371, 3080, 0, 0, 0, 0, 0, 0, 0, 0, 0, 0, 0, 0, 0], "count": 2019, "sum": 122701}, {"date": "20220225", "label": "", "histogram": [7871, 107598, 1081, 3102, 0, 0, 0, 0, 0, 0, 0, 0, 0, 0, 0, 0, 0], "count": 1980, "sum": 119066}, {"date": "20220226", "label": "", "histogram": [5729, 95467, 525, 1427, 0, 0, 0, 0, 0, 0, 0, 0, 0, 0, 0, 0, 0], "count": 1912, "sum": 100798}, {"date": "20220227", "label": "", "histogram": [6202, 101036, 216, 990, 0, 0, 0, 0, 0, 0, 0, 0, 0, 0, 0, 0, 0], "count": 1967, "sum": 104438}, {"date": "20220228", "label": "", "histogram": [6211, 94228, 640, 2038, 0, 0, 0, 0, 0, 0, 0, 0, 0, 0, 0, 0, 0], "count": 2074, "sum": 101622}, {"date": "20220301", "label": "", "histogram": [6019, 100351, 475, 3476, 0, 0, 0, 0, 0, 0, 0, 0, 0, 0, 0, 0, 0], "count": 2069, "sum": 111729}, {"date": "20220302", "label": "", "histogram": [9422, 95826, 433, 2324, 0, 0, 0, 0, 0, 0, 0, 0, 0, 0, 0, 0, 0], "count": 1998, "sum": 103664}, {"date": "20220303", "label": "", "histogram": [6889, 93235, 973, 1987, 0, 0, 0, 0, 0, 0, 0, 0, 0, 0, 0, 0, 0], "count": 1910, "sum": 101142}, {"date": "20220304", "label": "", "histogram": [4648, 87418, 463, 3207, 0, 0, 0, 0, 0, 0, 0, 0, 0, 0, 0, 0, 0], "count": 1992, "sum": 97965}, {"date": "20220305", "label": "", "histogram": [5679, 93512, 249, 2675, 0, 0, 0, 0, 0, 0, 0, 0, 0, 0, 0, 0, 0], "count": 1676, "sum": 102035}, {"date": "20220306", "label": "", "histogram": [7600, 65595, 320, 2726, 0, 0, 0, 0, 0, 0, 0, 0, 0, 0, 0, 0, 0], "count": 1415, "sum": 74413}, {"date": "20220307", "label": "", "histogram": [7224, 75060, 546, 2261, 0, 0, 0, 0, 0, 0, 0, 0, 0, 0, 0, 0, 0], "count": 1526, "sum": 82935}, {"date": "20220308", "label": "", "histogram": [4879, 74975, 1103, 3423, 0, 0, 0, 0, 0, 0, 0, 0, 0, 0, 0, 0, 0], "count": 1735, "sum": 87450}, {"date": "20220309", "label": "", "histogram": [5935, 70633, 832, 1236, 0, 0, 0, 0, 0, 0, 0, 0, 0, 0, 0, 0, 0], "count": 1607, "sum": 76005}, {"date": "20220310", "label": "", "histogram": [5368, 68665, 1104, 2016, 0, 0, 0, 0, 0, 0, 0, 0, 0, 0, 0, 0, 0], "count": 1633, "sum": 76921}, {"date": "20220311", "label": "", "histogram": [3925, 73103, 1479, 1336, 0, 0, 0, 0, 0, 0, 0, 0, 0, 0, 0, 0, 0], "count": 1645, "sum": 80069}, {"date": "20220312", "label": "", "histogram": [4983, 72270, 368, 53414, 0, 0, 0, 0, 0, 0, 0, 0, 0, 0, 0, 0, 0], "count": 1485, "sum": 233248}, {"date": "20220313", "label": "", "histogram": [5503, 69942, 420, 2084, 0, 0, 0, 0, 0, 0, 0, 0, 0, 0, 0, 0, 0], "count": 1448, "sum": 77034}, {"date": "20220314", "label": "", "histogram": [5119, 71066, 3106, 4167, 0, 0, 0, 0, 0, 0, 0, 0, 0, 0, 0, 0, 0], "count": 1524, "sum": 89779}, {"date": "20220315", "label": "", "histogram": [7894, 69838, 2186, 2006, 0, 0, 0, 0, 0, 0, 0, 0, 0, 0, 0, 0, 0], "count": 1532, "sum": 80228}, {"date": "20220316", "label": "", "histogram": [34716, 64208, 655, 3294, 0, 0, 0, 0, 0, 0, 0, 0, 0, 0, 0, 0, 0], "count": 1416, "sum": 75400}, {"date": "20220317", "label": "", "histogram": [5506, 68199, 619, 2611, 0, 0, 0, 0, 0, 0, 0, 0, 0, 0, 0, 0, 0], "count": 1398, "sum": 77270}, {"date": "20220318", "label": "", "histogram": [8048, 60659, 369, 3306, 0, 0, 0, 0, 0, 0, 0, 0, 0, 0, 0, 0, 0], "count": 1236, "sum": 71315}, {"date": "20220319", "label": "", "histogram": [5950, 47510, 293, 3019, 0, 0, 0, 0, 0, 0, 0, 0, 0, 0, 0, 0, 0], "count": 1114, "sum": 57153}, {"date": "20220320", "label": "", "histogram": [5586, 49837, 262, 2174, 0, 0, 0, 0, 0, 0, 0, 0, 0, 0, 0, 0, 0], "count": 1078, "sum": 56883}, {"date": "20220321", "label": "", "histogram": [6942, 52894, 437, 9566, 0, 0, 0, 0, 0, 0, 0, 0, 0, 0, 0, 0, 0], "count": 1181, "sum": 82466}, {"date": "20220322", "label": "", "histogram": [7073, 51206, 655, 2747, 0, 0, 0, 0, 0, 0, 0, 0, 0, 0, 0, 0, 0], "count": 1205, "sum": 60757}, {"date": "20220323", "label": "", "histogram": [6433, 52305, 677, 1920, 0, 0, 0, 0, 0, 0, 0, 0, 0, 0, 0, 0, 0], "count": 1115, "sum": 59419}, {"date": "20220324", "label": "", "histogram": [5160, 38381, 298, 1719, 0, 0, 0, 0, 0, 0, 0, 0, 0, 0, 0, 0, 0], "count": 966, "sum": 44134}, {"date": "20220325", "label": "", "histogram": [7418, 39309, 502, 2475, 0, 0, 0, 0, 0, 0, 0, 0, 0, 0, 0, 0, 0], "count": 933, "sum": 47738}, {"date": "20220326", "label": "", "histogram": [13818, 40073, 312, 1589, 0, 0, 0, 0, 0, 0, 0, 0, 0, 0, 0, 0, 0], "count": 768, "sum": 45464}, {"date": "20220327", "label": "", "histogram": [3822, 37081, 404, 2375, 0, 0, 0, 0, 0, 0, 0, 0, 0, 0, 0, 0, 0], "count": 813, "sum": 45014}, {"date": "20220328", "label": "", "histogram": [5791, 39492, 336, 2270, 0, 0, 0, 0, 0, 0, 0, 0, 0, 0, 0, 0, 0], "count": 830, "sum": 46974}, {"date": "20220329", "label": "", "histogram": [5119, 37790, 387, 2177, 0, 0, 0, 0, 0, 0, 0, 0, 0, 0, 0, 0, 0], "count": 871, "sum": 45095}, {"date": "20220330", "label": "", "histogram": [3564, 36779, 351, 1157, 0, 0, 0, 0, 0, 0, 0, 0, 0, 0, 0, 0, 0], "count": 810, "sum": 40952}, {"date": "20220331", "label": "", "histogram": [4400, 37999, 585, 2626, 0, 0, 0, 0, 0, 0, 0, 0, 0, 0, 0, 0, 0], "count": 838, "sum": 47047}, {"date": "20220401", "label": "", "histogram": [4928, 38138, 242, 3083, 0, 0, 0, 0, 0, 0, 0, 0, 0, 0, 0, 0, 0], "count": 792, "sum": 47871}, {"date": "20220402", "label": "", "histogram": [4309, 32540, 148, 2463, 0, 0, 0, 0, 0, 0, 0, 0, 0, 0, 0, 0, 0], "count": 707, "sum": 40225}, {"date": "20220403", "label": "", "histogram": [4637, 36162, 236, 2978, 0, 0, 0, 0, 0, 0, 0, 0, 0, 0, 0, 0, 0], "count": 720, "sum": 45568}, {"date": "20220404", "label": "", "histogram": [4704, 38830, 457, 975, 0, 0, 0, 0, 0, 0, 0, 0, 0, 0, 0, 0, 0], "count": 788, "sum": 42669}, {"date": "20220405", "label": "", "histogram": [4109, 33328, 318, 2038, 0, 0, 0, 0, 0, 0, 0, 0, 0, 0, 0, 0, 0], "count": 864, "sum": 40078}, {"date": "20220406", "label": "", "histogram": [3407, 37920, 774, 2381, 0, 0, 0, 0, 0, 0, 0, 0, 0, 0, 0, 0, 0], "count": 782, "sum": 46611}, {"date": "20220407", "label": "", "histogram": [5090, 37471, 214, 3572, 0, 0, 0, 0, 0, 0, 0, 0, 0, 0, 0, 0, 0], "count": 777, "sum": 48615}, {"date": "20220408", "label": "", "histogram": [4447, 37321, 396, 2745, 0, 0, 0, 0, 0, 0, 0, 0, 0, 0, 0, 0, 0], "count": 742, "sum": 46348}, {"date": "20220409", "label": "", "histogram": [3513, 35258, 205, 2285, 0, 0, 0, 0, 0, 0, 0, 0, 0, 0, 0, 0, 0], "count": 633, "sum": 42523}, {"date": "20220410", "label": "", "histogram": [4558, 33854, 50, 1893, 0, 0, 0, 0, 0, 0, 0, 0, 0, 0, 0, 0, 0], "count": 687, "sum": 39633}, {"date": "20220411", "label": "", "histogram": [4146, 38218, 189, 1881, 0, 0, 0, 0, 0, 0, 0, 0, 0, 0, 0, 0, 0], "count": 724, "sum": 44239}, {"date": "20220412", "label": "", "histogram": [3727, 34508, 369, 1334, 0, 0, 0, 0, 0, 0, 0, 0, 0, 0, 0, 0, 0], "count": 759, "sum": 39248}, {"date": "20220413", "label": "", "histogram": [3893, 35191, 281, 1221, 0, 0, 0, 0, 0, 0, 0, 0, 0, 0, 0, 0, 0], "count": 678, "sum": 39416}, {"date": "20220414", "label": "", "histogram": [4328, 35610, 223, 1466, 0, 0, 0, 0, 0, 0, 0, 0, 0, 0, 0, 0, 0], "count": 611, "sum": 40454}, {"date": "20220415", "label": "", "histogram": [5563, 35203, 225, 4794, 0, 0, 0, 0, 0, 0, 0, 0, 0, 0, 0, 0, 0], "count": 616, "sum": 50035}, {"date": "20220416", "label": "", "histogram": [3832, 31813, 303, 2993, 0, 0, 0, 0, 0, 0, 0, 0, 0, 0, 0, 0, 0], "count": 566, "sum": 41398}, {"date": "20220417", "label": "", "histogram": [4169, 27875, 173, 1253, 0, 0, 0, 0, 0, 0, 0, 0, 0, 0, 0, 0, 0], "count": 489, "sum": 31980}, {"date": "20220418", "label": "", "histogram": [5809, 31570, 512, 2576, 0, 0, 0, 0, 0, 0, 0, 0, 0, 0, 0, 0, 0], "count": 598, "sum": 40322}, {"date": "20220419", "label": "", "histogram": [4456, 31863, 296, 1059, 0, 0, 0, 0, 0, 0, 0, 0, 0, 0, 0, 0, 0], "count": 596, "sum": 35632}, {"date": "20220420", "label": "", "histogram": [4773, 33222, 190, 1712, 0, 0, 0, 0, 0, 0, 0, 0, 0, 0, 0, 0, 0], "count": 572, "sum": 38738}, {"date": "20220421", "label": "", "histogram": [3723, 28272, 257, 1948, 0, 0, 0, 0, 0, 0, 0, 0, 0, 0, 0, 0, 0], "count": 590, "sum": 34630}, {"date": "20220422", "label": "", "histogram": [3032, 25593, 404, 3340, 0, 0, 0, 0, 0, 0, 0, 0, 0, 0, 0, 0, 0], "count": 516, "sum": 36421}, {"date": "20220423", "label": "", "histogram": [3539, 24769, 179, 2001, 0, 0, 0, 0, 0, 0, 0, 0, 0, 0, 0, 0, 0], "count": 474, "sum": 31130}, {"date": "20220424", "label": "", "histogram": [3958, 27427, 425, 1974, 0, 0, 0, 0, 0, 0, 0, 0, 0, 0, 0, 0, 0], "count": 508, "sum": 34199}, {"date": "20220425", "label": "", "histogram": [3197, 27027, 182, 5432, 0, 0, 0, 0, 0, 0, 0, 0, 0, 0, 0, 0, 0], "count": 511, "sum": 43687}, {"date": "20220426", "label": "", "histogram": [4614, 25491, 474, 3293, 0, 0, 0, 0, 0, 0, 0, 0, 0, 0, 0, 0, 0], "count": 504, "sum": 36318}, {"date": "20220427", "label": "", "histogram": [4692, 28029, 268, 2404, 0, 0, 0, 0, 0, 0, 0, 0, 0, 0, 0, 0, 0], "count": 596, "sum": 35777}, {"date": "20220428", "label": "", "histogram": [3662, 28256, 120, 1829, 0, 0, 0, 0, 0, 0, 0, 0, 0, 0, 0, 0, 0], "count": 501, "sum": 33983}, {"date": "20220429", "label": "", "histogram": [3515, 24190, 275, 1157, 0, 0, 0, 0, 0, 0, 0, 0, 0, 0, 0, 0, 0], "count": 493, "sum": 28211}, {"date": "20220430", "label": "", "histogram": [2041, 20321, 178, 1625, 0, 0, 0, 0, 0, 0, 0, 0, 0, 0, 0, 0, 0], "count": 361, "sum": 25552}, {"date": "20220501", "label": "", "histogram": [1833, 21408, 136, 1912, 0, 0, 0, 0, 0, 0, 0, 0, 0, 0, 0, 0, 0], "count": 398, "sum": 27416}, {"date": "20220502", "label": "", "histogram": [2988, 21021, 932, 1379, 0, 0, 0, 0, 0, 0, 0, 0, 0, 0, 0, 0, 0], "count": 409, "sum": 27022}, {"date": "20220503", "label": "", "histogram": [4102, 24294, 104, 1359, 0, 0, 0, 0, 0, 0, 0, 0, 0, 0, 0, 0, 0], "count": 534, "sum": 28579}, {"date": "20220504", "label": "", "histogram": [3099, 24735, 688, 1238, 0, 0, 0, 0, 0, 0, 0, 0, 0, 0, 0, 0, 0], "count": 469, "sum": 29825}, {"date": "20220505", "label": "", "histogram": [3216, 24976, 323, 982, 0, 0, 0, 0, 0, 0, 0, 0, 0, 0, 0, 0, 0], "count": 525, "sum": 28568}, {"date": "20220506", "label": "", "histogram": [3522, 24655, 222, 1038, 0, 0, 0, 0, 0, 0, 0, 0, 0, 0, 0, 0, 0], "count": 436, "sum": 28213}, {"date": "20220507", "label": "", "histogram": [2617, 25930, 53, 549, 0, 0, 0, 0, 0, 0, 0, 0, 0, 0, 0, 0, 0], "count": 467, "sum": 27683}, {"date": "20220508", "label": "", "histogram": [2105, 22298, 298, 747, 0, 0, 0, 0, 0, 0, 0, 0, 0, 0, 0, 0, 0], "count": 358, "sum": 25135}, {"date": "20220509", "label": "", "histogram": [2400, 22118, 227, 1650, 0, 0, 0, 0, 0, 0, 0, 0, 0, 0, 0, 0, 0], "count": 459, "sum": 27522}, {"date": "20220510", "label": "", "histogram": [3887, 30352, 166, 3340, 0, 0, 0, 0, 0, 0, 0, 0, 0, 0, 0, 0, 0], "count": 443, "sum": 40704}, {"date": "20220511", "label": "", "histogram": [3482, 21390, 242, 5333, 0, 0, 0, 0, 0, 0, 0, 0, 0, 0, 0, 0, 0], "count": 471, "sum": 37873}, {"date": "20220512", "label": "", "histogram": [3576, 34239, 120, 981, 0, 0, 0, 0, 0, 0, 0, 0, 0, 0, 0, 0, 0], "count": 487, "sum": 37422}, {"date": "20220513", "label": "", "histogram": [1366, 19793, 140, 1135, 0, 0, 0, 0, 0, 0, 0, 0, 0, 0, 0, 0, 0], "count": 434, "sum": 23478}, {"date": "20220514", "label": "", "histogram": [3143, 24329, 225, 767, 0, 0, 0, 0, 0, 0, 0, 0, 0, 0, 0, 0, 0], "count": 398, "sum": 27080}, {"date": "20220515", "label": "", "histogram": [2085, 22079, 573, 2355, 0, 0, 0, 0, 0, 0, 0, 0, 0, 0, 0, 0, 0], "count": 412, "sum": 30290}, {"date": "20220516", "label": "", "histogram": [2421, 21274, 629, 977, 0, 0, 0, 0, 0, 0, 0, 0, 0, 0, 0, 0, 0], "count": 467, "sum": 25463}, {"date": "20220517", "label": "", "histogram": [2469, 23936, 283, 863, 0, 0, 0, 0, 0, 0, 0, 0, 0, 0, 0, 0, 0], "count": 483, "sum": 27091}, {"date": "20220518", "label": "", "histogram": [2254, 23813, 413, 688, 0, 0, 0, 0, 0, 0, 0, 0, 0, 0, 0, 0, 0], "count": 452, "sum": 26703}, {"date": "20220519", "label": "", "histogram": [2130, 23674, 355, 623, 0, 0, 0, 0, 0, 0, 0, 0, 0, 0, 0, 0, 0], "count": 484, "sum": 26253}, {"date": "20220520", "label": "", "histogram": [1661, 23618, 371, 4063, 0, 0, 0, 0, 0, 0, 0, 0, 0, 0, 0, 0, 0], "count": 429, "sum": 36549}, {"date": "20220521", "label": "", "histogram": [2653, 21903, 223, 1601, 0, 0, 0, 0, 0, 0, 0, 0, 0, 0, 0, 0, 0], "count": 362, "sum": 27152}, {"date": "20220522", "label": "", "histogram": [1608, 18484, 126, 843, 0, 0, 0, 0, 0, 0, 0, 0, 0, 0, 0, 0, 0], "count": 362, "sum": 21265}, {"date": "20220523", "label": "", "histogram": [2225, 19867, 176, 1785, 0, 0, 0, 0, 0, 0, 0, 0, 0, 0, 0, 0, 0], "count": 460, "sum": 25574}, {"date": "20220524", "label": "", "histogram": [1568, 18803, 305, 891, 0, 0, 0, 0, 0, 0, 0, 0, 0, 0, 0, 0, 0], "count": 397, "sum": 22086}, {"date": "20220525", "label": "", "histogram": [1915, 19792, 133, 1374, 0, 0, 0, 0, 0, 0, 0, 0, 0, 0, 0, 0, 0], "count": 432, "sum": 24180}, {"date": "20220526", "label": "", "histogram": [2347, 20169, 118, 951, 0, 0, 0, 0, 0, 0, 0, 0, 0, 0, 0, 0, 0], "count": 416, "sum": 23258}, {"date": "20220527", "label": "", "histogram": [2785, 21105, 214, 932, 0, 0, 0, 0, 0, 0, 0, 0, 0, 0, 0, 0, 0], "count": 406, "sum": 24329}, {"date": "20220528", "label": "", "histogram": [1274, 14770, 61, 1419, 0, 0, 0, 0, 0, 0, 0, 0, 0, 0, 0, 0, 0], "count": 347, "sum": 19149}, {"date": "20220529", "label": "", "histogram": [2698, 17369, 30, 1946, 0, 0, 0, 0, 0, 0, 0, 0, 0, 0, 0, 0, 0], "count": 358, "sum": 23267}, {"date": "20220530", "label": "", "histogram": [3314, 16812, 125, 4868, 0, 0, 0, 0, 0, 0, 0, 0, 0, 0, 0, 0, 0], "count": 388, "sum": 31666}, {"date": "20220531", "label": "", "histogram": [2102, 20701, 138, 557, 0, 0, 0, 0, 0, 0, 0, 0, 0, 0, 0, 0, 0], "count": 433, "sum": 22648}, {"date": "20220601", "label": "", "histogram": [2617, 20406, 150, 1647, 0, 0, 0, 0, 0, 0, 0, 0, 0, 0, 0, 0, 0], "count": 423, "sum": 25647}, {"date": "20220602", "label": "", "histogram": [1757, 18088, 1110, 1842, 0, 0, 0, 0, 0, 0, 0, 0, 0, 0, 0, 0, 0], "count": 400, "sum": 25834}, {"date": "20220603", "label": "", "histogram": [1839, 16231, 1386, 2921, 0, 0, 0, 0, 0, 0, 0, 0, 0, 0, 0, 0, 0], "count": 374, "sum": 27766}, {"date": "20220604", "label": "", "histogram": [1135, 16375, 34, 4259, 0, 0, 0, 0, 0, 0, 0, 0, 0, 0, 0, 0, 0], "count": 307, "sum": 29220}, {"date": "20220605", "label": "", "histogram": [1722, 17544, 85, 733, 0, 0, 0, 0, 0, 0, 0, 0, 0, 0, 0, 0, 0], "count": 345, "sum": 19913}, {"date": "20220606", "label": "", "histogram": [1237, 17164, 147, 668, 0, 0, 0, 0, 0, 0, 0, 0, 0, 0, 0, 0, 0], "count": 357, "sum": 19462}, {"date": "20220607", "label": "", "histogram": [1856, 19049, 233, 1029, 0, 0, 0, 0, 0, 0, 0, 0, 0, 0, 0, 0, 0], "count": 389, "sum": 22602}, {"date": "20220608", "label": "", "histogram": [1305, 17108, 121, 658, 0, 0, 0, 0, 0, 0, 0, 0, 0, 0, 0, 0, 0], "count": 371, "sum": 19324}, {"date": "20220609", "label": "", "histogram": [965, 15603, 691, 292, 0, 0, 0, 0, 0, 0, 0, 0, 0, 0, 0, 0, 0], "count": 362, "sum": 17861}, {"date": "20220610", "label": "", "histogram": [1537, 18893, 71, 1123, 0, 0, 0, 0, 0, 0, 0, 0, 0, 0, 0, 0, 0], "count": 374, "sum": 22404}, {"date": "20220611", "label": "", "histogram": [3145, 12613, 142, 346, 0, 0, 0, 0, 0, 0, 0, 0, 0, 0, 0, 0, 0], "count": 299, "sum": 13935}, {"date": "20220612", "label": "", "histogram": [2770, 11773, 29, 1111, 0, 0, 0, 0, 0, 0, 0, 0, 0, 0, 0, 0, 0], "count": 339, "sum": 15164}, {"date": "20220613", "label": "", "histogram": [958, 16187, 78, 856, 0, 0, 0, 0, 0, 0, 0, 0, 0, 0, 0, 0, 0], "count": 355, "sum": 18911}, {"date": "20220614", "label": "", "histogram": [814, 12444, 33, 726, 0, 0, 0, 0, 0, 0, 0, 0, 0, 0, 0, 0, 0], "count": 339, "sum": 14688}, {"date": "20220615", "label": "", "histogram": [1554, 16923, 102, 481, 0, 0, 0, 0, 0, 0, 0, 0, 0, 0, 0, 0, 0], "count": 387, "sum": 18570}, {"date": "20220616", "label": "", "histogram": [2318, 16231, 29, 1267, 0, 0, 0, 0, 0, 0, 0, 0, 0, 0, 0, 0, 0], "count": 353, "sum": 20090}, {"date": "20220617", "label": "", "histogram": [1501, 14948, 32, 940, 0, 0, 0, 0, 0, 0, 0, 0, 0, 0, 0, 0, 0], "count": 319, "sum": 17832}, {"date": "20220618", "label": "", "histogram": [1438, 10926, 8, 805, 0, 0, 0, 0, 0, 0, 0, 0, 0, 0, 0, 0, 0], "count": 246, "sum": 13357}, {"date": "20220619", "label": "", "histogram": [858, 10180, 9, 463, 0, 0, 0, 0, 0, 0, 0, 0, 0, 0, 0, 0, 0], "count": 223, "sum": 11587}, {"date": "20220620", "label": "", "histogram": [1661, 15437, 64, 457, 0, 0, 0, 0, 0, 0, 0, 0, 0, 0, 0, 0, 0], "count": 372, "sum": 16936}, {"date": "20220621", "label": "", "histogram": [1245, 15951, 63, 536, 0, 0, 0, 0, 0, 0, 0, 0, 0, 0, 0, 0, 0], "count": 325, "sum": 17685}, {"date": "20220622", "label": "", "histogram": [1324, 16360, 142, 481, 0, 0, 0, 0, 0, 0, 0, 0, 0, 0, 0, 0, 0], "count": 338, "sum": 18087}, {"date": "20220623", "label": "", "histogram": [1459, 14820, 271, 611, 0, 0, 0, 0, 0, 0, 0, 0, 0, 0, 0, 0, 0], "count": 313, "sum": 17195}, {"date": "20220624", "label": "", "histogram": [1680, 17889, 160, 1719, 0, 0, 0, 0, 0, 0, 0, 0, 0, 0, 0, 0, 0], "count": 351, "sum": 23366}, {"date": "20220625", "label": "", "histogram": [872, 15119, 90, 338, 0, 0, 0, 0, 0, 0, 0, 0, 0, 0, 0, 0, 0], "count": 257, "sum": 16313}, {"date": "20220626", "label": "", "histogram": [1563, 12952, 89, 459, 0, 0, 0, 0, 0, 0, 0, 0, 0, 0, 0, 0, 0], "count": 228, "sum": 14507}, {"date": "20220627", "label": "", "histogram": [2092, 13439, 252, 430, 0, 0, 0, 0, 0, 0, 0, 0, 0, 0, 0, 0, 0], "count": 310, "sum": 15233}, {"date": "20220628", "label": "", "histogram": [922, 14738, 166, 535, 0, 0, 0, 0, 0, 0, 0, 0, 0, 0, 0, 0, 0], "count": 375, "sum": 16675}, {"date": "20220629", "label": "", "histogram": [1331, 12089, 697, 433, 0, 0, 0, 0, 0, 0, 0, 0, 0, 0, 0, 0, 0], "count": 308, "sum": 14782}, {"date": "20220630", "label": "", "histogram": [1060, 15117, 226, 428, 0, 0, 0, 0, 0, 0, 0, 0, 0, 0, 0, 0, 0], "count": 320, "sum": 16853}, {"date": "20220701", "label": "", "histogram": [1284, 12359, 760, 426, 0, 0, 0, 0, 0, 0, 0, 0, 0, 0, 0, 0, 0], "count": 288, "sum": 15157}, {"date": "20220702", "label": "", "histogram": [1798, 12195, 641, 928, 0, 0, 0, 0, 0, 0, 0, 0, 0, 0, 0, 0, 0], "count": 279, "sum": 16261}, {"date": "20220703", "label": "", "histogram": [842, 9885, 382, 341, 0, 0, 0, 0, 0, 0, 0, 0, 0, 0, 0, 0, 0], "count": 259, "sum": 11672}, {"date": "20220704", "label": "", "histogram": [1056, 12191, 118, 215, 0, 0, 0, 0, 0, 0, 0, 0, 0, 0, 0, 0, 0], "count": 278, "sum": 13072}, {"date": "20220705", "label": "", "histogram": [1432, 14383, 85, 81, 0, 0, 0, 0, 0, 0, 0, 0, 0, 0, 0, 0, 0], "count": 293, "sum": 14796}, {"date": "20220706", "label": "", "histogram": [1814, 13912, 76, 732, 0, 0, 0, 0, 0, 0, 0, 0, 0, 0, 0, 0, 0], "count": 284, "sum": 16260}, {"date": "20220707", "label": "", "histogram": [1866, 13470, 220, 526, 0, 0, 0, 0, 0, 0, 0, 0, 0, 0, 0, 0, 0], "count": 293, "sum": 15488}, {"date": "20220708", "label": "", "histogram": [1108, 12469, 75, 131, 0, 0, 0, 0, 0, 0, 0, 0, 0, 0, 0, 0, 0], "count": 238, "sum": 13012}, {"date": "20220709", "label": "", "histogram": [837, 9916, 86, 619, 0, 0, 0, 0, 0, 0, 0, 0, 0, 0, 0, 0, 0], "count": 244, "sum": 11945}, {"date": "20220710", "label": "", "histogram": [1222, 13356, 62, 2, 0, 0, 0, 0, 0, 0, 0, 0, 0, 0, 0, 0, 0], "count": 229, "sum": 13486}, {"date": "20220711", "label": "", "histogram": [1670, 12371, 117, 1, 0, 0, 0, 0, 0, 0, 0, 0, 0, 0, 0, 0, 0], "count": 303, "sum": 12608}, {"date": "20220712", "label": "", "histogram": [2116, 8691, 141, 35, 0, 0, 0, 0, 0, 0, 0, 0, 0, 0, 0, 0, 0], "count": 244, "sum": 9078}, {"date": "20220713", "label": "", "histogram": [766, 8216, 71, 26, 0, 0, 0, 0, 0, 0, 0, 0, 0, 0, 0, 0, 0], "count": 223, "sum": 8436}, {"date": "20220714", "label": "", "histogram": [1599, 9071, 67, 61, 0, 0, 0, 0, 0, 0, 0, 0, 0, 0, 0, 0, 0], "count": 237, "sum": 9388}, {"date": "20220715", "label": "", "histogram": [970, 11047, 38, 0, 0, 0, 0, 0, 0, 0, 0, 0, 0, 0, 0, 0, 0], "count": 241, "sum": 11123}, {"date": "20220716", "label": "", "histogram": [1883, 11041, 21, 105, 0, 0, 0, 0, 0, 0, 0, 0, 0, 0, 0, 0, 0], "count": 249, "sum": 11398}, {"date": "20220717", "label": "", "histogram": [1105, 10851, 120, 1, 0, 0, 0, 0, 0, 0, 0, 0, 0, 0, 0, 0, 0], "count": 224, "sum": 11094}, {"date": "20220718", "label": "", "histogram": [1544, 13953, 19, 36, 0, 0, 0, 0, 0, 0, 0, 0, 0, 0, 0, 0, 0], "count": 262, "sum": 14099}], "buckets": [0, 1, 2, 3, 4, 5, 6, 7, 8, 9, 10, 11, 12, 13, 14, 15, 16], "kind": "enumerated", "description": "HTTP result of OCSP, etc.. (0=canceled, 1=OK, 2=FAILED, 3=internal-error)"}